<?xml version='1.0' encoding='utf-8'?>
<tv generator-info-name="Surf EPG (Open-Meteo)" generator-info-url="https://raw.githubusercontent.com/OiErU/weather-dashboard/main">
  <channel id="ericeira-surfline">
    <display-name>Surfline Ericeira</display-name>
    <icon src="https://raw.githubusercontent.com/OiErU/weather-dashboard/main/logos/ericeira.png?v=2" />
  </channel>
  <channel id="ericeira-meo">
    <display-name>MEO Ericeira</display-name>
    <icon src="https://raw.githubusercontent.com/OiErU/weather-dashboard/main/logos/ericeira.png?v=2" />
  </channel>
  <channel id="supertubos-surfline">
    <display-name>Surfline Supertubos</display-name>
    <icon src="https://raw.githubusercontent.com/OiErU/weather-dashboard/main/logos/supertubos.png?v=2" />
  </channel>
  <channel id="supertubos-meo">
    <display-name>MEO Supertubos</display-name>
    <icon src="https://raw.githubusercontent.com/OiErU/weather-dashboard/main/logos/supertubos.png?v=2" />
  </channel>
  <channel id="molheleste-surfline">
    <display-name>Surfline Molhe Leste</display-name>
    <icon src="https://raw.githubusercontent.com/OiErU/weather-dashboard/main/logos/molheleste.png?v=2" />
  </channel>
  <channel id="molheleste-meo">
    <display-name>MEO Molhe Leste</display-name>
    <icon src="https://raw.githubusercontent.com/OiErU/weather-dashboard/main/logos/molheleste.png?v=2" />
  </channel>
  <channel id="baia-meo">
    <display-name>MEO Baia</display-name>
    <icon src="https://raw.githubusercontent.com/OiErU/weather-dashboard/main/logos/baleal.png?v=2" />
  </channel>
  <channel id="cantinho-surfline">
    <display-name>Surfline Cantinho</display-name>
    <icon src="https://raw.githubusercontent.com/OiErU/weather-dashboard/main/logos/cantinho.png?v=2" />
  </channel>
  <channel id="cantinho-meo">
    <display-name>MEO Cantinho</display-name>
    <icon src="https://raw.githubusercontent.com/OiErU/weather-dashboard/main/logos/cantinho.png?v=2" />
  </channel>
  <channel id="baleal-surfline">
    <display-name>Surfline Baleal</display-name>
    <icon src="https://raw.githubusercontent.com/OiErU/weather-dashboard/main/logos/baleal.png?v=2" />
  </channel>
  <channel id="lagide-surfline">
    <display-name>Surfline Lagide</display-name>
    <icon src="https://raw.githubusercontent.com/OiErU/weather-dashboard/main/logos/lagide.png?v=2" />
  </channel>
  <channel id="lagide-meo">
    <display-name>MEO Lagide</display-name>
    <icon src="https://raw.githubusercontent.com/OiErU/weather-dashboard/main/logos/lagide.png?v=2" />
  </channel>
  <programme start="20260217000000 +0000" stop="20260217060000 +0000" channel="ericeira-surfline">
    <title lang="en">🌊 2.6m @ 12s ONSHORE</title>
    <desc lang="en">That onshore wind will make those 2.6m waves a bumpy, short-lived affair, perfect for practicing duckdives.

🌊 Swell: 2.6m @ 12s
💨 Wind: 8.0km/h WNW (ONSHORE)
💨 Gusts: 17.0km/h
🌊 Wind waves: 0.1m</desc>
    <icon src="https://raw.githubusercontent.com/OiErU/weather-dashboard/main/posters/ericeira_poster.jpg" />
  </programme>
  <programme start="20260217000000 +0000" stop="20260217060000 +0000" channel="ericeira-meo">
    <title lang="en">🌊 2.6m @ 12s ONSHORE</title>
    <desc lang="en">That onshore wind will make those 2.6m waves a bumpy, short-lived affair, perfect for practicing duckdives.

🌊 Swell: 2.6m @ 12s
💨 Wind: 8.0km/h WNW (ONSHORE)
💨 Gusts: 17.0km/h
🌊 Wind waves: 0.1m</desc>
    <icon src="https://raw.githubusercontent.com/OiErU/weather-dashboard/main/posters/ericeira_poster.jpg" />
  </programme>
  <programme start="20260217000000 +0000" stop="20260217060000 +0000" channel="supertubos-surfline">
    <title lang="en">🌊 2.5m @ 14s ONSHORE</title>
    <desc lang="en">With 2.5 meters and onshore breeze, Supertubos will be offering thrills, spills, and perhaps a broken fin or two.

🌊 Swell: 2.5m @ 14s
💨 Wind: 11.0km/h W (ONSHORE)
💨 Gusts: 13.0km/h
🌊 Wind waves: 0.2m</desc>
    <icon src="https://raw.githubusercontent.com/OiErU/weather-dashboard/main/posters/supertubos_poster.jpg" />
  </programme>
  <programme start="20260217000000 +0000" stop="20260217060000 +0000" channel="supertubos-meo">
    <title lang="en">🌊 2.5m @ 14s ONSHORE</title>
    <desc lang="en">With 2.5 meters and onshore breeze, Supertubos will be offering thrills, spills, and perhaps a broken fin or two.

🌊 Swell: 2.5m @ 14s
💨 Wind: 11.0km/h W (ONSHORE)
💨 Gusts: 13.0km/h
🌊 Wind waves: 0.2m</desc>
    <icon src="https://raw.githubusercontent.com/OiErU/weather-dashboard/main/posters/supertubos_poster.jpg" />
  </programme>
  <programme start="20260217000000 +0000" stop="20260217060000 +0000" channel="molheleste-surfline">
    <title lang="en">🌊 2.5m @ 14s ONSHORE</title>
    <desc lang="en">2.  5m and onshore; could be worse, but probably just another Molhe Monday of closeouts and chop.

🌊 Swell: 2.5m @ 14s
💨 Wind: 11.0km/h W (ONSHORE)
💨 Gusts: 13.0km/h
🌊 Wind waves: 0.2m</desc>
    <icon src="https://raw.githubusercontent.com/OiErU/weather-dashboard/main/posters/molheleste_poster.jpg" />
  </programme>
  <programme start="20260217000000 +0000" stop="20260217060000 +0000" channel="molheleste-meo">
    <title lang="en">🌊 2.5m @ 14s ONSHORE</title>
    <desc lang="en">2.  5m and onshore; could be worse, but probably just another Molhe Monday of closeouts and chop.

🌊 Swell: 2.5m @ 14s
💨 Wind: 11.0km/h W (ONSHORE)
💨 Gusts: 13.0km/h
🌊 Wind waves: 0.2m</desc>
    <icon src="https://raw.githubusercontent.com/OiErU/weather-dashboard/main/posters/molheleste_poster.jpg" />
  </programme>
  <programme start="20260217000000 +0000" stop="20260217060000 +0000" channel="baia-meo">
    <title lang="en">🌊 2.5m @ 14s CROSS</title>
    <desc lang="en">With that crosswind on a 2.5m swell, today's session will likely involve more duck diving than riding.

🌊 Swell: 2.5m @ 14s
💨 Wind: 11.0km/h W (CROSS)
💨 Gusts: 13.0km/h
🌊 Wind waves: 0.2m</desc>
    <icon src="https://raw.githubusercontent.com/OiErU/weather-dashboard/main/posters/baleal_poster.jpg" />
  </programme>
  <programme start="20260217000000 +0000" stop="20260217060000 +0000" channel="cantinho-surfline">
    <title lang="en">🌊 2.5m @ 14s CROSS</title>
    <desc lang="en">2.  5m and onshore? Might be good for spectating some wipeouts.

🌊 Swell: 2.5m @ 14s
💨 Wind: 11.0km/h W (CROSS)
💨 Gusts: 13.0km/h
🌊 Wind waves: 0.2m</desc>
    <icon src="https://raw.githubusercontent.com/OiErU/weather-dashboard/main/posters/cantinho_poster.jpg" />
  </programme>
  <programme start="20260217000000 +0000" stop="20260217060000 +0000" channel="cantinho-meo">
    <title lang="en">🌊 2.5m @ 14s CROSS</title>
    <desc lang="en">2.  5m and onshore? Might be good for spectating some wipeouts.

🌊 Swell: 2.5m @ 14s
💨 Wind: 11.0km/h W (CROSS)
💨 Gusts: 13.0km/h
🌊 Wind waves: 0.2m</desc>
    <icon src="https://raw.githubusercontent.com/OiErU/weather-dashboard/main/posters/cantinho_poster.jpg" />
  </programme>
  <programme start="20260217000000 +0000" stop="20260217060000 +0000" channel="baleal-surfline">
    <title lang="en">🌊 2.5m @ 14s CROSS</title>
    <desc lang="en">Those 2.5m waves might offer a few rides before the wind turns them into something resembling a washing machine.

🌊 Swell: 2.5m @ 14s
💨 Wind: 11.0km/h W (CROSS)
💨 Gusts: 13.0km/h
🌊 Wind waves: 0.2m</desc>
    <icon src="https://raw.githubusercontent.com/OiErU/weather-dashboard/main/posters/baleal_poster.jpg" />
  </programme>
  <programme start="20260217000000 +0000" stop="20260217060000 +0000" channel="lagide-surfline">
    <title lang="en">🌊 2.5m @ 14s CROSS</title>
    <desc lang="en">At 2.5m with that wind, Lagide will be offering a masterclass in survival today.

🌊 Swell: 2.5m @ 14s
💨 Wind: 11.0km/h W (CROSS)
💨 Gusts: 13.0km/h
🌊 Wind waves: 0.2m</desc>
    <icon src="https://raw.githubusercontent.com/OiErU/weather-dashboard/main/posters/lagide_poster.jpg" />
  </programme>
  <programme start="20260217000000 +0000" stop="20260217060000 +0000" channel="lagide-meo">
    <title lang="en">🌊 2.5m @ 14s CROSS</title>
    <desc lang="en">At 2.5m with that wind, Lagide will be offering a masterclass in survival today.

🌊 Swell: 2.5m @ 14s
💨 Wind: 11.0km/h W (CROSS)
💨 Gusts: 13.0km/h
🌊 Wind waves: 0.2m</desc>
    <icon src="https://raw.githubusercontent.com/OiErU/weather-dashboard/main/posters/lagide_poster.jpg" />
  </programme>
  <programme start="20260217060000 +0000" stop="20260217120000 +0000" channel="ericeira-surfline">
    <title lang="en">🌊 2.1m @ 14s ONSHORE</title>
    <desc lang="en">2.  1m and onshore? A good day for watching the tourists get pummelled.

🌊 Swell: 2.1m @ 14s
💨 Wind: 4.0km/h W (ONSHORE)
💨 Gusts: 12.0km/h
🌊 Wind waves: 0.0m</desc>
    <icon src="https://raw.githubusercontent.com/OiErU/weather-dashboard/main/posters/ericeira_poster.jpg" />
  </programme>
  <programme start="20260217060000 +0000" stop="20260217120000 +0000" channel="ericeira-meo">
    <title lang="en">🌊 2.1m @ 14s ONSHORE</title>
    <desc lang="en">2.  1m and onshore? A good day for watching the tourists get pummelled.

🌊 Swell: 2.1m @ 14s
💨 Wind: 4.0km/h W (ONSHORE)
💨 Gusts: 12.0km/h
🌊 Wind waves: 0.0m</desc>
    <icon src="https://raw.githubusercontent.com/OiErU/weather-dashboard/main/posters/ericeira_poster.jpg" />
  </programme>
  <programme start="20260217060000 +0000" stop="20260217120000 +0000" channel="supertubos-surfline">
    <title lang="en">🌊 2.1m @ 14s ONSHORE</title>
    <desc lang="en">Two-metre Supertubos with onshore wind: good for a beating, not much else.

🌊 Swell: 2.1m @ 14s
💨 Wind: 9.0km/h W (ONSHORE)
💨 Gusts: 17.0km/h
🌊 Wind waves: 0.1m</desc>
    <icon src="https://raw.githubusercontent.com/OiErU/weather-dashboard/main/posters/supertubos_poster.jpg" />
  </programme>
  <programme start="20260217060000 +0000" stop="20260217120000 +0000" channel="supertubos-meo">
    <title lang="en">🌊 2.1m @ 14s ONSHORE</title>
    <desc lang="en">Two-metre Supertubos with onshore wind: good for a beating, not much else.

🌊 Swell: 2.1m @ 14s
💨 Wind: 9.0km/h W (ONSHORE)
💨 Gusts: 17.0km/h
🌊 Wind waves: 0.1m</desc>
    <icon src="https://raw.githubusercontent.com/OiErU/weather-dashboard/main/posters/supertubos_poster.jpg" />
  </programme>
  <programme start="20260217060000 +0000" stop="20260217120000 +0000" channel="molheleste-surfline">
    <title lang="en">🌊 2.1m @ 14s ONSHORE</title>
    <desc lang="en">With 2.1m and onshore wind, Molhe Leste is probably offering more closeouts than barrels today.

🌊 Swell: 2.1m @ 14s
💨 Wind: 9.0km/h W (ONSHORE)
💨 Gusts: 17.0km/h
🌊 Wind waves: 0.1m</desc>
    <icon src="https://raw.githubusercontent.com/OiErU/weather-dashboard/main/posters/molheleste_poster.jpg" />
  </programme>
  <programme start="20260217060000 +0000" stop="20260217120000 +0000" channel="molheleste-meo">
    <title lang="en">🌊 2.1m @ 14s ONSHORE</title>
    <desc lang="en">With 2.1m and onshore wind, Molhe Leste is probably offering more closeouts than barrels today.

🌊 Swell: 2.1m @ 14s
💨 Wind: 9.0km/h W (ONSHORE)
💨 Gusts: 17.0km/h
🌊 Wind waves: 0.1m</desc>
    <icon src="https://raw.githubusercontent.com/OiErU/weather-dashboard/main/posters/molheleste_poster.jpg" />
  </programme>
  <programme start="20260217060000 +0000" stop="20260217120000 +0000" channel="baia-meo">
    <title lang="en">🌊 2.1m @ 14s ONSHORE</title>
    <desc lang="en">With that onshore breeze, those 2.1m waves will likely be a closeout soup today.

🌊 Swell: 2.1m @ 14s
💨 Wind: 9.0km/h W (ONSHORE)
💨 Gusts: 17.0km/h
🌊 Wind waves: 0.1m</desc>
    <icon src="https://raw.githubusercontent.com/OiErU/weather-dashboard/main/posters/baleal_poster.jpg" />
  </programme>
  <programme start="20260217060000 +0000" stop="20260217120000 +0000" channel="cantinho-surfline">
    <title lang="en">🌊 2.1m @ 14s CROSS</title>
    <desc lang="en">At 2.1m with that wind, Cantinho might provide some closeout entertainment for the brave.

🌊 Swell: 2.1m @ 14s
💨 Wind: 9.0km/h W (CROSS)
💨 Gusts: 17.0km/h
🌊 Wind waves: 0.1m</desc>
    <icon src="https://raw.githubusercontent.com/OiErU/weather-dashboard/main/posters/cantinho_poster.jpg" />
  </programme>
  <programme start="20260217060000 +0000" stop="20260217120000 +0000" channel="cantinho-meo">
    <title lang="en">🌊 2.1m @ 14s CROSS</title>
    <desc lang="en">At 2.1m with that wind, Cantinho might provide some closeout entertainment for the brave.

🌊 Swell: 2.1m @ 14s
💨 Wind: 9.0km/h W (CROSS)
💨 Gusts: 17.0km/h
🌊 Wind waves: 0.1m</desc>
    <icon src="https://raw.githubusercontent.com/OiErU/weather-dashboard/main/posters/cantinho_poster.jpg" />
  </programme>
  <programme start="20260217060000 +0000" stop="20260217120000 +0000" channel="baleal-surfline">
    <title lang="en">🌊 2.1m @ 14s CROSS</title>
    <desc lang="en">That 2.1m swell and crosswind suggest Baleal Norte's serving up a good helping of chop today.

🌊 Swell: 2.1m @ 14s
💨 Wind: 9.0km/h W (CROSS)
💨 Gusts: 17.0km/h
🌊 Wind waves: 0.1m</desc>
    <icon src="https://raw.githubusercontent.com/OiErU/weather-dashboard/main/posters/baleal_poster.jpg" />
  </programme>
  <programme start="20260217060000 +0000" stop="20260217120000 +0000" channel="lagide-surfline">
    <title lang="en">🌊 2.1m @ 14s CROSS</title>
    <desc lang="en">That 2.1m swell and cross-wind might produce a few rideable faces before the closeouts rearrange my fillings.

🌊 Swell: 2.1m @ 14s
💨 Wind: 9.0km/h W (CROSS)
💨 Gusts: 17.0km/h
🌊 Wind waves: 0.1m</desc>
    <icon src="https://raw.githubusercontent.com/OiErU/weather-dashboard/main/posters/lagide_poster.jpg" />
  </programme>
  <programme start="20260217060000 +0000" stop="20260217120000 +0000" channel="lagide-meo">
    <title lang="en">🌊 2.1m @ 14s CROSS</title>
    <desc lang="en">That 2.1m swell and cross-wind might produce a few rideable faces before the closeouts rearrange my fillings.

🌊 Swell: 2.1m @ 14s
💨 Wind: 9.0km/h W (CROSS)
💨 Gusts: 17.0km/h
🌊 Wind waves: 0.1m</desc>
    <icon src="https://raw.githubusercontent.com/OiErU/weather-dashboard/main/posters/lagide_poster.jpg" />
  </programme>
  <programme start="20260217120000 +0000" stop="20260217180000 +0000" channel="ericeira-surfline">
    <title lang="en">🌊 2.7m @ 14s ONSHORE</title>
    <desc lang="en">With that much onshore wind on a 2.7m swell, you'll be fighting chop more than riding waves today.

🌊 Swell: 2.7m @ 14s
💨 Wind: 6.0km/h WSW (ONSHORE)
💨 Gusts: 13.0km/h
🌊 Wind waves: 0.0m</desc>
    <icon src="https://raw.githubusercontent.com/OiErU/weather-dashboard/main/posters/ericeira_poster.jpg" />
  </programme>
  <programme start="20260217120000 +0000" stop="20260217180000 +0000" channel="ericeira-meo">
    <title lang="en">🌊 2.7m @ 14s ONSHORE</title>
    <desc lang="en">With that much onshore wind on a 2.7m swell, you'll be fighting chop more than riding waves today.

🌊 Swell: 2.7m @ 14s
💨 Wind: 6.0km/h WSW (ONSHORE)
💨 Gusts: 13.0km/h
🌊 Wind waves: 0.0m</desc>
    <icon src="https://raw.githubusercontent.com/OiErU/weather-dashboard/main/posters/ericeira_poster.jpg" />
  </programme>
  <programme start="20260217120000 +0000" stop="20260217180000 +0000" channel="supertubos-surfline">
    <title lang="en">🌊 2.6m @ 14s ONSHORE</title>
    <desc lang="en">2.  6 meters and onshore wind – the shorebreak should be sporting, if you fancy a beating.

🌊 Swell: 2.6m @ 14s
💨 Wind: 10.0km/h SW (ONSHORE)
💨 Gusts: 16.0km/h
🌊 Wind waves: 0.0m</desc>
    <icon src="https://raw.githubusercontent.com/OiErU/weather-dashboard/main/posters/supertubos_poster.jpg" />
  </programme>
  <programme start="20260217120000 +0000" stop="20260217180000 +0000" channel="supertubos-meo">
    <title lang="en">🌊 2.6m @ 14s ONSHORE</title>
    <desc lang="en">2.  6 meters and onshore wind – the shorebreak should be sporting, if you fancy a beating.

🌊 Swell: 2.6m @ 14s
💨 Wind: 10.0km/h SW (ONSHORE)
💨 Gusts: 16.0km/h
🌊 Wind waves: 0.0m</desc>
    <icon src="https://raw.githubusercontent.com/OiErU/weather-dashboard/main/posters/supertubos_poster.jpg" />
  </programme>
  <programme start="20260217120000 +0000" stop="20260217180000 +0000" channel="molheleste-surfline">
    <title lang="en">🌊 2.6m @ 14s CROSS</title>
    <desc lang="en">2.6 meters and onshore wind suggests a washing machine, best watched from the café.

🌊 Swell: 2.6m @ 14s
💨 Wind: 10.0km/h SW (CROSS)
💨 Gusts: 16.0km/h
🌊 Wind waves: 0.0m</desc>
    <icon src="https://raw.githubusercontent.com/OiErU/weather-dashboard/main/posters/molheleste_poster.jpg" />
  </programme>
  <programme start="20260217120000 +0000" stop="20260217180000 +0000" channel="molheleste-meo">
    <title lang="en">🌊 2.6m @ 14s CROSS</title>
    <desc lang="en">2.6 meters and onshore wind suggests a washing machine, best watched from the café.

🌊 Swell: 2.6m @ 14s
💨 Wind: 10.0km/h SW (CROSS)
💨 Gusts: 16.0km/h
🌊 Wind waves: 0.0m</desc>
    <icon src="https://raw.githubusercontent.com/OiErU/weather-dashboard/main/posters/molheleste_poster.jpg" />
  </programme>
  <programme start="20260217120000 +0000" stop="20260217180000 +0000" channel="baia-meo">
    <title lang="en">🌊 2.6m @ 14s CROSS</title>
    <desc lang="en">At 2.6m with that wind, today's session will likely involve more swimming than riding.

🌊 Swell: 2.6m @ 14s
💨 Wind: 10.0km/h SW (CROSS)
💨 Gusts: 16.0km/h
🌊 Wind waves: 0.0m</desc>
    <icon src="https://raw.githubusercontent.com/OiErU/weather-dashboard/main/posters/baleal_poster.jpg" />
  </programme>
  <programme start="20260217120000 +0000" stop="20260217180000 +0000" channel="cantinho-surfline">
    <title lang="en">🌊 2.6m @ 14s CROSS</title>
    <desc lang="en">Those 2.6 meters are definitely showing, but that crosswind will just make things interesting, in the pejorative sense.

🌊 Swell: 2.6m @ 14s
💨 Wind: 10.0km/h SW (CROSS)
💨 Gusts: 16.0km/h
🌊 Wind waves: 0.0m</desc>
    <icon src="https://raw.githubusercontent.com/OiErU/weather-dashboard/main/posters/cantinho_poster.jpg" />
  </programme>
  <programme start="20260217120000 +0000" stop="20260217180000 +0000" channel="cantinho-meo">
    <title lang="en">🌊 2.6m @ 14s CROSS</title>
    <desc lang="en">Those 2.6 meters are definitely showing, but that crosswind will just make things interesting, in the pejorative sense.

🌊 Swell: 2.6m @ 14s
💨 Wind: 10.0km/h SW (CROSS)
💨 Gusts: 16.0km/h
🌊 Wind waves: 0.0m</desc>
    <icon src="https://raw.githubusercontent.com/OiErU/weather-dashboard/main/posters/cantinho_poster.jpg" />
  </programme>
  <programme start="20260217120000 +0000" stop="20260217180000 +0000" channel="baleal-surfline">
    <title lang="en">⭐⭐ 2.6m @ 14s OFFSHORE</title>
    <desc lang="en">Yeah, you could probably get a 2.6m wave or two out there today, if you're feeling lucky.

🌊 Swell: 2.6m @ 14s
💨 Wind: 10.0km/h SW (OFFSHORE)
💨 Gusts: 16.0km/h
🌊 Wind waves: 0.0m

📋 Clean conditions with offshore wind</desc>
    <icon src="https://raw.githubusercontent.com/OiErU/weather-dashboard/main/posters/baleal_poster.jpg" />
  </programme>
  <programme start="20260217120000 +0000" stop="20260217180000 +0000" channel="lagide-surfline">
    <title lang="en">⭐⭐ 2.6m @ 14s OFFSHORE</title>
    <desc lang="en">With a 2.6m swell and offshore wind, Lagide might offer a few rideable moments before the inevitable closeout lottery begins.

🌊 Swell: 2.6m @ 14s
💨 Wind: 10.0km/h SW (OFFSHORE)
💨 Gusts: 16.0km/h
🌊 Wind waves: 0.0m

📋 Clean conditions with offshore wind</desc>
    <icon src="https://raw.githubusercontent.com/OiErU/weather-dashboard/main/posters/lagide_poster.jpg" />
  </programme>
  <programme start="20260217120000 +0000" stop="20260217180000 +0000" channel="lagide-meo">
    <title lang="en">⭐⭐ 2.6m @ 14s OFFSHORE</title>
    <desc lang="en">With a 2.6m swell and offshore wind, Lagide might offer a few rideable moments before the inevitable closeout lottery begins.

🌊 Swell: 2.6m @ 14s
💨 Wind: 10.0km/h SW (OFFSHORE)
💨 Gusts: 16.0km/h
🌊 Wind waves: 0.0m

📋 Clean conditions with offshore wind</desc>
    <icon src="https://raw.githubusercontent.com/OiErU/weather-dashboard/main/posters/lagide_poster.jpg" />
  </programme>
  <programme start="20260217180000 +0000" stop="20260218000000 +0000" channel="ericeira-surfline">
    <title lang="en">🌊 2.3m @ 12s ONSHORE</title>
    <desc lang="en">With that 2.3m swell and onshore breeze, today's Ribeira session will either be a closeout festival or a full-body exfoliation.

🌊 Swell: 2.3m @ 12s
💨 Wind: 7.0km/h WSW (ONSHORE)
💨 Gusts: 18.0km/h
🌊 Wind waves: 0.0m</desc>
    <icon src="https://raw.githubusercontent.com/OiErU/weather-dashboard/main/posters/ericeira_poster.jpg" />
  </programme>
  <programme start="20260217180000 +0000" stop="20260218000000 +0000" channel="ericeira-meo">
    <title lang="en">🌊 2.3m @ 12s ONSHORE</title>
    <desc lang="en">With that 2.3m swell and onshore breeze, today's Ribeira session will either be a closeout festival or a full-body exfoliation.

🌊 Swell: 2.3m @ 12s
💨 Wind: 7.0km/h WSW (ONSHORE)
💨 Gusts: 18.0km/h
🌊 Wind waves: 0.0m</desc>
    <icon src="https://raw.githubusercontent.com/OiErU/weather-dashboard/main/posters/ericeira_poster.jpg" />
  </programme>
  <programme start="20260217180000 +0000" stop="20260218000000 +0000" channel="supertubos-surfline">
    <title lang="en">🌊 2.2m @ 12s ONSHORE</title>
    <desc lang="en">The 2.2m swell is here, but the wind suggests it'll be more like battling a washing machine than riding Supertubos today.

🌊 Swell: 2.2m @ 12s
💨 Wind: 6.0km/h WSW (ONSHORE)
💨 Gusts: 19.0km/h
🌊 Wind waves: 0.0m</desc>
    <icon src="https://raw.githubusercontent.com/OiErU/weather-dashboard/main/posters/supertubos_poster.jpg" />
  </programme>
  <programme start="20260217180000 +0000" stop="20260218000000 +0000" channel="supertubos-meo">
    <title lang="en">🌊 2.2m @ 12s ONSHORE</title>
    <desc lang="en">The 2.2m swell is here, but the wind suggests it'll be more like battling a washing machine than riding Supertubos today.

🌊 Swell: 2.2m @ 12s
💨 Wind: 6.0km/h WSW (ONSHORE)
💨 Gusts: 19.0km/h
🌊 Wind waves: 0.0m</desc>
    <icon src="https://raw.githubusercontent.com/OiErU/weather-dashboard/main/posters/supertubos_poster.jpg" />
  </programme>
  <programme start="20260217180000 +0000" stop="20260218000000 +0000" channel="molheleste-surfline">
    <title lang="en">🌊 2.2m @ 12s ONSHORE</title>
    <desc lang="en">That 2.2m swell and onshore wind suggest it's more about survival than surfing today.

🌊 Swell: 2.2m @ 12s
💨 Wind: 6.0km/h WSW (ONSHORE)
💨 Gusts: 19.0km/h
🌊 Wind waves: 0.0m</desc>
    <icon src="https://raw.githubusercontent.com/OiErU/weather-dashboard/main/posters/molheleste_poster.jpg" />
  </programme>
  <programme start="20260217180000 +0000" stop="20260218000000 +0000" channel="molheleste-meo">
    <title lang="en">🌊 2.2m @ 12s ONSHORE</title>
    <desc lang="en">That 2.2m swell and onshore wind suggest it's more about survival than surfing today.

🌊 Swell: 2.2m @ 12s
💨 Wind: 6.0km/h WSW (ONSHORE)
💨 Gusts: 19.0km/h
🌊 Wind waves: 0.0m</desc>
    <icon src="https://raw.githubusercontent.com/OiErU/weather-dashboard/main/posters/molheleste_poster.jpg" />
  </programme>
  <programme start="20260217180000 +0000" stop="20260218000000 +0000" channel="baia-meo">
    <title lang="en">🌊 2.2m @ 12s CROSS</title>
    <desc lang="en">Two-metre plus waves and that wind? I'll watch the carnage with an espresso, thanks.

🌊 Swell: 2.2m @ 12s
💨 Wind: 6.0km/h WSW (CROSS)
💨 Gusts: 19.0km/h
🌊 Wind waves: 0.0m</desc>
    <icon src="https://raw.githubusercontent.com/OiErU/weather-dashboard/main/posters/baleal_poster.jpg" />
  </programme>
  <programme start="20260217180000 +0000" stop="20260218000000 +0000" channel="cantinho-surfline">
    <title lang="en">🌊 2.2m @ 12s CROSS</title>
    <desc lang="en">With that swell and wind, the 2.2 meter waves will likely be closing out spectacularly today.

🌊 Swell: 2.2m @ 12s
💨 Wind: 6.0km/h WSW (CROSS)
💨 Gusts: 19.0km/h
🌊 Wind waves: 0.0m</desc>
    <icon src="https://raw.githubusercontent.com/OiErU/weather-dashboard/main/posters/cantinho_poster.jpg" />
  </programme>
  <programme start="20260217180000 +0000" stop="20260218000000 +0000" channel="cantinho-meo">
    <title lang="en">🌊 2.2m @ 12s CROSS</title>
    <desc lang="en">With that swell and wind, the 2.2 meter waves will likely be closing out spectacularly today.

🌊 Swell: 2.2m @ 12s
💨 Wind: 6.0km/h WSW (CROSS)
💨 Gusts: 19.0km/h
🌊 Wind waves: 0.0m</desc>
    <icon src="https://raw.githubusercontent.com/OiErU/weather-dashboard/main/posters/cantinho_poster.jpg" />
  </programme>
  <programme start="20260217180000 +0000" stop="20260218000000 +0000" channel="baleal-surfline">
    <title lang="en">🌊 2.2m @ 12s CROSS</title>
    <desc lang="en">Two-metre-plus and a crosswind; might be entertaining for a few beatings.

🌊 Swell: 2.2m @ 12s
💨 Wind: 6.0km/h WSW (CROSS)
💨 Gusts: 19.0km/h
🌊 Wind waves: 0.0m</desc>
    <icon src="https://raw.githubusercontent.com/OiErU/weather-dashboard/main/posters/baleal_poster.jpg" />
  </programme>
  <programme start="20260217180000 +0000" stop="20260218000000 +0000" channel="lagide-surfline">
    <title lang="en">🌊 2.2m @ 12s CROSS</title>
    <desc lang="en">That 2.2m swell and onshore breeze suggests a good day for bodyboarding, if you enjoy being bounced around like a sock in a washing machine.

🌊 Swell: 2.2m @ 12s
💨 Wind: 6.0km/h WSW (CROSS)
💨 Gusts: 19.0km/h
🌊 Wind waves: 0.0m</desc>
    <icon src="https://raw.githubusercontent.com/OiErU/weather-dashboard/main/posters/lagide_poster.jpg" />
  </programme>
  <programme start="20260217180000 +0000" stop="20260218000000 +0000" channel="lagide-meo">
    <title lang="en">🌊 2.2m @ 12s CROSS</title>
    <desc lang="en">That 2.2m swell and onshore breeze suggests a good day for bodyboarding, if you enjoy being bounced around like a sock in a washing machine.

🌊 Swell: 2.2m @ 12s
💨 Wind: 6.0km/h WSW (CROSS)
💨 Gusts: 19.0km/h
🌊 Wind waves: 0.0m</desc>
    <icon src="https://raw.githubusercontent.com/OiErU/weather-dashboard/main/posters/lagide_poster.jpg" />
  </programme>
  <programme start="20260218000000 +0000" stop="20260218060000 +0000" channel="ericeira-surfline">
    <title lang="en">🌊 2.1m @ 12s ONSHORE</title>
    <desc lang="en">With that onshore breeze fighting the 2.1m swell, today will be more of a workout than a wave-riding experience.

🌊 Swell: 2.1m @ 12s
💨 Wind: 9.0km/h WSW (ONSHORE)
💨 Gusts: 19.0km/h
🌊 Wind waves: 0.3m</desc>
    <icon src="https://raw.githubusercontent.com/OiErU/weather-dashboard/main/posters/ericeira_poster.jpg" />
  </programme>
  <programme start="20260218000000 +0000" stop="20260218060000 +0000" channel="ericeira-meo">
    <title lang="en">🌊 2.1m @ 12s ONSHORE</title>
    <desc lang="en">With that onshore breeze fighting the 2.1m swell, today will be more of a workout than a wave-riding experience.

🌊 Swell: 2.1m @ 12s
💨 Wind: 9.0km/h WSW (ONSHORE)
💨 Gusts: 19.0km/h
🌊 Wind waves: 0.3m</desc>
    <icon src="https://raw.githubusercontent.com/OiErU/weather-dashboard/main/posters/ericeira_poster.jpg" />
  </programme>
  <programme start="20260218000000 +0000" stop="20260218060000 +0000" channel="supertubos-surfline">
    <title lang="en">🌊 2.0m @ 12s ONSHORE</title>
    <desc lang="en">With that 2.0m swell and onshore breeze, Supertubos will likely be a washing machine today; enjoy the sand.

🌊 Swell: 2.0m @ 12s
💨 Wind: 11.0km/h SW (ONSHORE)
💨 Gusts: 17.0km/h
🌊 Wind waves: 0.4m</desc>
    <icon src="https://raw.githubusercontent.com/OiErU/weather-dashboard/main/posters/supertubos_poster.jpg" />
  </programme>
  <programme start="20260218000000 +0000" stop="20260218060000 +0000" channel="supertubos-meo">
    <title lang="en">🌊 2.0m @ 12s ONSHORE</title>
    <desc lang="en">With that 2.0m swell and onshore breeze, Supertubos will likely be a washing machine today; enjoy the sand.

🌊 Swell: 2.0m @ 12s
💨 Wind: 11.0km/h SW (ONSHORE)
💨 Gusts: 17.0km/h
🌊 Wind waves: 0.4m</desc>
    <icon src="https://raw.githubusercontent.com/OiErU/weather-dashboard/main/posters/supertubos_poster.jpg" />
  </programme>
  <programme start="20260218000000 +0000" stop="20260218060000 +0000" channel="molheleste-surfline">
    <title lang="en">🌊 2.0m @ 12s CROSS</title>
    <desc lang="en">With that crosswind, today's 2.0m swell will likely be a closeout lottery near the north jetty.

🌊 Swell: 2.0m @ 12s
💨 Wind: 11.0km/h SW (CROSS)
💨 Gusts: 17.0km/h
🌊 Wind waves: 0.4m</desc>
    <icon src="https://raw.githubusercontent.com/OiErU/weather-dashboard/main/posters/molheleste_poster.jpg" />
  </programme>
  <programme start="20260218000000 +0000" stop="20260218060000 +0000" channel="molheleste-meo">
    <title lang="en">🌊 2.0m @ 12s CROSS</title>
    <desc lang="en">With that crosswind, today's 2.0m swell will likely be a closeout lottery near the north jetty.

🌊 Swell: 2.0m @ 12s
💨 Wind: 11.0km/h SW (CROSS)
💨 Gusts: 17.0km/h
🌊 Wind waves: 0.4m</desc>
    <icon src="https://raw.githubusercontent.com/OiErU/weather-dashboard/main/posters/molheleste_poster.jpg" />
  </programme>
  <programme start="20260218000000 +0000" stop="20260218060000 +0000" channel="baia-meo">
    <title lang="en">🌊 2.0m @ 12s CROSS</title>
    <desc lang="en">Two meters with that wind? Surfing's probably off, unless you enjoy bouncing down the beach.

🌊 Swell: 2.0m @ 12s
💨 Wind: 11.0km/h SW (CROSS)
💨 Gusts: 17.0km/h
🌊 Wind waves: 0.4m</desc>
    <icon src="https://raw.githubusercontent.com/OiErU/weather-dashboard/main/posters/baleal_poster.jpg" />
  </programme>
  <programme start="20260218000000 +0000" stop="20260218060000 +0000" channel="cantinho-surfline">
    <title lang="en">🌊 2.0m @ 12s CROSS</title>
    <desc lang="en">Two meters with that wind? Best to watch the kitesurfers earn their wipeouts today.

🌊 Swell: 2.0m @ 12s
💨 Wind: 11.0km/h SW (CROSS)
💨 Gusts: 17.0km/h
🌊 Wind waves: 0.4m</desc>
    <icon src="https://raw.githubusercontent.com/OiErU/weather-dashboard/main/posters/cantinho_poster.jpg" />
  </programme>
  <programme start="20260218000000 +0000" stop="20260218060000 +0000" channel="cantinho-meo">
    <title lang="en">🌊 2.0m @ 12s CROSS</title>
    <desc lang="en">Two meters with that wind? Best to watch the kitesurfers earn their wipeouts today.

🌊 Swell: 2.0m @ 12s
💨 Wind: 11.0km/h SW (CROSS)
💨 Gusts: 17.0km/h
🌊 Wind waves: 0.4m</desc>
    <icon src="https://raw.githubusercontent.com/OiErU/weather-dashboard/main/posters/cantinho_poster.jpg" />
  </programme>
  <programme start="20260218000000 +0000" stop="20260218060000 +0000" channel="baleal-surfline">
    <title lang="en">⭐⭐ 2.0m @ 12s OFFSHORE</title>
    <desc lang="en">Two meter swell with offshore wind? Might get a few, might get cleaned up; depends how brave you're feeling.

🌊 Swell: 2.0m @ 12s
💨 Wind: 11.0km/h SW (OFFSHORE)
💨 Gusts: 17.0km/h
🌊 Wind waves: 0.4m

📋 Clean conditions with offshore wind</desc>
    <icon src="https://raw.githubusercontent.com/OiErU/weather-dashboard/main/posters/baleal_poster.jpg" />
  </programme>
  <programme start="20260218000000 +0000" stop="20260218060000 +0000" channel="lagide-surfline">
    <title lang="en">⭐⭐ 2.0m @ 12s OFFSHORE</title>
    <desc lang="en">Lagide might offer a few rideable 2.0m faces, assuming the wind doesn't tear them apart.

🌊 Swell: 2.0m @ 12s
💨 Wind: 11.0km/h SW (OFFSHORE)
💨 Gusts: 17.0km/h
🌊 Wind waves: 0.4m

📋 Clean conditions with offshore wind</desc>
    <icon src="https://raw.githubusercontent.com/OiErU/weather-dashboard/main/posters/lagide_poster.jpg" />
  </programme>
  <programme start="20260218000000 +0000" stop="20260218060000 +0000" channel="lagide-meo">
    <title lang="en">⭐⭐ 2.0m @ 12s OFFSHORE</title>
    <desc lang="en">Lagide might offer a few rideable 2.0m faces, assuming the wind doesn't tear them apart.

🌊 Swell: 2.0m @ 12s
💨 Wind: 11.0km/h SW (OFFSHORE)
💨 Gusts: 17.0km/h
🌊 Wind waves: 0.4m

📋 Clean conditions with offshore wind</desc>
    <icon src="https://raw.githubusercontent.com/OiErU/weather-dashboard/main/posters/lagide_poster.jpg" />
  </programme>
  <programme start="20260218060000 +0000" stop="20260218120000 +0000" channel="ericeira-surfline">
    <title lang="en">🌊 2.1m @ 12s CROSS</title>
    <desc lang="en">2.  1 meters and a crosswind; might be good for a swim, or maybe just a beating.

🌊 Swell: 2.1m @ 12s
💨 Wind: 11.0km/h SSW (CROSS)
💨 Gusts: 23.0km/h
🌊 Wind waves: 0.3m</desc>
    <icon src="https://raw.githubusercontent.com/OiErU/weather-dashboard/main/posters/ericeira_poster.jpg" />
  </programme>
  <programme start="20260218060000 +0000" stop="20260218120000 +0000" channel="ericeira-meo">
    <title lang="en">🌊 2.1m @ 12s CROSS</title>
    <desc lang="en">2.  1 meters and a crosswind; might be good for a swim, or maybe just a beating.

🌊 Swell: 2.1m @ 12s
💨 Wind: 11.0km/h SSW (CROSS)
💨 Gusts: 23.0km/h
🌊 Wind waves: 0.3m</desc>
    <icon src="https://raw.githubusercontent.com/OiErU/weather-dashboard/main/posters/ericeira_poster.jpg" />
  </programme>
  <programme start="20260218060000 +0000" stop="20260218120000 +0000" channel="supertubos-surfline">
    <title lang="en">🌊 1.7m @ 12s ONSHORE</title>
    <desc lang="en">With that onshore breeze, these 1.7m waves will likely be more effort than enjoyment today.

🌊 Swell: 1.7m @ 12s
💨 Wind: 17.0km/h SSW (ONSHORE)
💨 Gusts: 26.0km/h
🌊 Wind waves: 0.5m</desc>
    <icon src="https://raw.githubusercontent.com/OiErU/weather-dashboard/main/posters/supertubos_poster.jpg" />
  </programme>
  <programme start="20260218060000 +0000" stop="20260218120000 +0000" channel="supertubos-meo">
    <title lang="en">🌊 1.7m @ 12s ONSHORE</title>
    <desc lang="en">With that onshore breeze, these 1.7m waves will likely be more effort than enjoyment today.

🌊 Swell: 1.7m @ 12s
💨 Wind: 17.0km/h SSW (ONSHORE)
💨 Gusts: 26.0km/h
🌊 Wind waves: 0.5m</desc>
    <icon src="https://raw.githubusercontent.com/OiErU/weather-dashboard/main/posters/supertubos_poster.jpg" />
  </programme>
  <programme start="20260218060000 +0000" stop="20260218120000 +0000" channel="molheleste-surfline">
    <title lang="en">🌊 1.7m @ 12s CROSS</title>
    <desc lang="en">The 1.7m swell might offer a ride or two before the wind turns it to chop suey.

🌊 Swell: 1.7m @ 12s
💨 Wind: 17.0km/h SSW (CROSS)
💨 Gusts: 26.0km/h
🌊 Wind waves: 0.5m</desc>
    <icon src="https://raw.githubusercontent.com/OiErU/weather-dashboard/main/posters/molheleste_poster.jpg" />
  </programme>
  <programme start="20260218060000 +0000" stop="20260218120000 +0000" channel="molheleste-meo">
    <title lang="en">🌊 1.7m @ 12s CROSS</title>
    <desc lang="en">The 1.7m swell might offer a ride or two before the wind turns it to chop suey.

🌊 Swell: 1.7m @ 12s
💨 Wind: 17.0km/h SSW (CROSS)
💨 Gusts: 26.0km/h
🌊 Wind waves: 0.5m</desc>
    <icon src="https://raw.githubusercontent.com/OiErU/weather-dashboard/main/posters/molheleste_poster.jpg" />
  </programme>
  <programme start="20260218060000 +0000" stop="20260218120000 +0000" channel="baia-meo">
    <title lang="en">🌊 1.7m @ 12s CROSS</title>
    <desc lang="en">1.  7 meters with that wind? Looks like Meio da Baía wants to rearrange some spines today.

🌊 Swell: 1.7m @ 12s
💨 Wind: 17.0km/h SSW (CROSS)
💨 Gusts: 26.0km/h
🌊 Wind waves: 0.5m</desc>
    <icon src="https://raw.githubusercontent.com/OiErU/weather-dashboard/main/posters/baleal_poster.jpg" />
  </programme>
  <programme start="20260218060000 +0000" stop="20260218120000 +0000" channel="cantinho-surfline">
    <title lang="en">⭐⭐ 1.7m @ 12s OFFSHORE</title>
    <desc lang="en">With that offshore, the 1.7m swell should offer a few ramps, assuming you enjoy getting sandblasted.

🌊 Swell: 1.7m @ 12s
💨 Wind: 17.0km/h SSW (OFFSHORE)
💨 Gusts: 26.0km/h
🌊 Wind waves: 0.5m

📋 Clean conditions with offshore wind</desc>
    <icon src="https://raw.githubusercontent.com/OiErU/weather-dashboard/main/posters/cantinho_poster.jpg" />
  </programme>
  <programme start="20260218060000 +0000" stop="20260218120000 +0000" channel="cantinho-meo">
    <title lang="en">⭐⭐ 1.7m @ 12s OFFSHORE</title>
    <desc lang="en">With that offshore, the 1.7m swell should offer a few ramps, assuming you enjoy getting sandblasted.

🌊 Swell: 1.7m @ 12s
💨 Wind: 17.0km/h SSW (OFFSHORE)
💨 Gusts: 26.0km/h
🌊 Wind waves: 0.5m

📋 Clean conditions with offshore wind</desc>
    <icon src="https://raw.githubusercontent.com/OiErU/weather-dashboard/main/posters/cantinho_poster.jpg" />
  </programme>
  <programme start="20260218060000 +0000" stop="20260218120000 +0000" channel="baleal-surfline">
    <title lang="en">⭐⭐ 1.7m @ 12s OFFSHORE</title>
    <desc lang="en">With 1.7m and offshore breeze, today's Baleal Norte is worth a paddle, maybe even a successful ride.

🌊 Swell: 1.7m @ 12s
💨 Wind: 17.0km/h SSW (OFFSHORE)
💨 Gusts: 26.0km/h
🌊 Wind waves: 0.5m

📋 Clean conditions with offshore wind</desc>
    <icon src="https://raw.githubusercontent.com/OiErU/weather-dashboard/main/posters/baleal_poster.jpg" />
  </programme>
  <programme start="20260218060000 +0000" stop="20260218120000 +0000" channel="lagide-surfline">
    <title lang="en">⭐⭐ 1.7m @ 12s OFFSHORE</title>
    <desc lang="en">Yeah, that 1.7m swell with offshore wind might be worth a paddle, if you enjoy being picky.

🌊 Swell: 1.7m @ 12s
💨 Wind: 17.0km/h SSW (OFFSHORE)
💨 Gusts: 26.0km/h
🌊 Wind waves: 0.5m

📋 Clean conditions with offshore wind</desc>
    <icon src="https://raw.githubusercontent.com/OiErU/weather-dashboard/main/posters/lagide_poster.jpg" />
  </programme>
  <programme start="20260218060000 +0000" stop="20260218120000 +0000" channel="lagide-meo">
    <title lang="en">⭐⭐ 1.7m @ 12s OFFSHORE</title>
    <desc lang="en">Yeah, that 1.7m swell with offshore wind might be worth a paddle, if you enjoy being picky.

🌊 Swell: 1.7m @ 12s
💨 Wind: 17.0km/h SSW (OFFSHORE)
💨 Gusts: 26.0km/h
🌊 Wind waves: 0.5m

📋 Clean conditions with offshore wind</desc>
    <icon src="https://raw.githubusercontent.com/OiErU/weather-dashboard/main/posters/lagide_poster.jpg" />
  </programme>
  <programme start="20260218120000 +0000" stop="20260218180000 +0000" channel="ericeira-surfline">
    <title lang="en">💨 2.0m @ 11s ONSHORE</title>
    <desc lang="en">At 2.0m with this wind, today will be more of a body-washing exercise than bodyboarding.

🌊 Swell: 2.0m @ 11s
💨 Wind: 30.0km/h SW (ONSHORE)
💨 Gusts: 59.0km/h
🌊 Wind waves: 0.9m

📋 Onshore wind making it messy</desc>
    <icon src="https://raw.githubusercontent.com/OiErU/weather-dashboard/main/posters/ericeira_poster.jpg" />
  </programme>
  <programme start="20260218120000 +0000" stop="20260218180000 +0000" channel="ericeira-meo">
    <title lang="en">💨 2.0m @ 11s ONSHORE</title>
    <desc lang="en">At 2.0m with this wind, today will be more of a body-washing exercise than bodyboarding.

🌊 Swell: 2.0m @ 11s
💨 Wind: 30.0km/h SW (ONSHORE)
💨 Gusts: 59.0km/h
🌊 Wind waves: 0.9m

📋 Onshore wind making it messy</desc>
    <icon src="https://raw.githubusercontent.com/OiErU/weather-dashboard/main/posters/ericeira_poster.jpg" />
  </programme>
  <programme start="20260218120000 +0000" stop="20260218180000 +0000" channel="supertubos-surfline">
    <title lang="en">💨 1.8m @ 12s ONSHORE</title>
    <desc lang="en">That 1.8m swell's fighting a losing battle against this wind, so bring a snorkel and a healthy dose of optimism.

🌊 Swell: 1.8m @ 12s
💨 Wind: 34.0km/h SW (ONSHORE)
💨 Gusts: 54.0km/h
🌊 Wind waves: 1.1m

📋 Onshore wind making it messy • Significant wind chop</desc>
    <icon src="https://raw.githubusercontent.com/OiErU/weather-dashboard/main/posters/supertubos_poster.jpg" />
  </programme>
  <programme start="20260218120000 +0000" stop="20260218180000 +0000" channel="supertubos-meo">
    <title lang="en">💨 1.8m @ 12s ONSHORE</title>
    <desc lang="en">That 1.8m swell's fighting a losing battle against this wind, so bring a snorkel and a healthy dose of optimism.

🌊 Swell: 1.8m @ 12s
💨 Wind: 34.0km/h SW (ONSHORE)
💨 Gusts: 54.0km/h
🌊 Wind waves: 1.1m

📋 Onshore wind making it messy • Significant wind chop</desc>
    <icon src="https://raw.githubusercontent.com/OiErU/weather-dashboard/main/posters/supertubos_poster.jpg" />
  </programme>
  <programme start="20260218120000 +0000" stop="20260218180000 +0000" channel="molheleste-surfline">
    <title lang="en">💨 1.8m @ 12s ONSHORE</title>
    <desc lang="en">With 1.8m waves and that wind, today will mostly involve getting sandblasted and tumbled dry.

🌊 Swell: 1.8m @ 12s
💨 Wind: 34.0km/h SW (ONSHORE)
💨 Gusts: 54.0km/h
🌊 Wind waves: 1.1m

📋 Onshore wind making it messy • Significant wind chop</desc>
    <icon src="https://raw.githubusercontent.com/OiErU/weather-dashboard/main/posters/molheleste_poster.jpg" />
  </programme>
  <programme start="20260218120000 +0000" stop="20260218180000 +0000" channel="molheleste-meo">
    <title lang="en">💨 1.8m @ 12s ONSHORE</title>
    <desc lang="en">With 1.8m waves and that wind, today will mostly involve getting sandblasted and tumbled dry.

🌊 Swell: 1.8m @ 12s
💨 Wind: 34.0km/h SW (ONSHORE)
💨 Gusts: 54.0km/h
🌊 Wind waves: 1.1m

📋 Onshore wind making it messy • Significant wind chop</desc>
    <icon src="https://raw.githubusercontent.com/OiErU/weather-dashboard/main/posters/molheleste_poster.jpg" />
  </programme>
  <programme start="20260218120000 +0000" stop="20260218180000 +0000" channel="baia-meo">
    <title lang="en">🌊 1.8m @ 12s CROSS</title>
    <desc lang="en">With 1.8m and that wind, you'll be battling more chop than wave today, probably.

🌊 Swell: 1.8m @ 12s
💨 Wind: 34.0km/h SW (CROSS)
💨 Gusts: 54.0km/h
🌊 Wind waves: 1.1m

📋 Significant wind chop</desc>
    <icon src="https://raw.githubusercontent.com/OiErU/weather-dashboard/main/posters/baleal_poster.jpg" />
  </programme>
  <programme start="20260218120000 +0000" stop="20260218180000 +0000" channel="cantinho-surfline">
    <title lang="en">🌊 1.8m @ 12s CROSS</title>
    <desc lang="en">That 1.8m swell with the cross-wind sounds like a good way to get sandblasted and frustrated.

🌊 Swell: 1.8m @ 12s
💨 Wind: 34.0km/h SW (CROSS)
💨 Gusts: 54.0km/h
🌊 Wind waves: 1.1m

📋 Significant wind chop</desc>
    <icon src="https://raw.githubusercontent.com/OiErU/weather-dashboard/main/posters/cantinho_poster.jpg" />
  </programme>
  <programme start="20260218120000 +0000" stop="20260218180000 +0000" channel="cantinho-meo">
    <title lang="en">🌊 1.8m @ 12s CROSS</title>
    <desc lang="en">That 1.8m swell with the cross-wind sounds like a good way to get sandblasted and frustrated.

🌊 Swell: 1.8m @ 12s
💨 Wind: 34.0km/h SW (CROSS)
💨 Gusts: 54.0km/h
🌊 Wind waves: 1.1m

📋 Significant wind chop</desc>
    <icon src="https://raw.githubusercontent.com/OiErU/weather-dashboard/main/posters/cantinho_poster.jpg" />
  </programme>
  <programme start="20260218120000 +0000" stop="20260218180000 +0000" channel="baleal-surfline">
    <title lang="en">⭐⭐ 1.8m @ 12s OFFSHORE</title>
    <desc lang="en">The 1.8m swell might offer a few ramps before the offshore wind eats them alive.

🌊 Swell: 1.8m @ 12s
💨 Wind: 34.0km/h SW (OFFSHORE)
💨 Gusts: 54.0km/h
🌊 Wind waves: 1.1m

📋 Clean conditions with offshore wind</desc>
    <icon src="https://raw.githubusercontent.com/OiErU/weather-dashboard/main/posters/baleal_poster.jpg" />
  </programme>
  <programme start="20260218120000 +0000" stop="20260218180000 +0000" channel="lagide-surfline">
    <title lang="en">⭐⭐ 1.8m @ 12s OFFSHORE</title>
    <desc lang="en">The 1.8m swell and offshore wind could be alright, if you enjoy a side of windburn with your wipeouts.

🌊 Swell: 1.8m @ 12s
💨 Wind: 34.0km/h SW (OFFSHORE)
💨 Gusts: 54.0km/h
🌊 Wind waves: 1.1m

📋 Clean conditions with offshore wind</desc>
    <icon src="https://raw.githubusercontent.com/OiErU/weather-dashboard/main/posters/lagide_poster.jpg" />
  </programme>
  <programme start="20260218120000 +0000" stop="20260218180000 +0000" channel="lagide-meo">
    <title lang="en">⭐⭐ 1.8m @ 12s OFFSHORE</title>
    <desc lang="en">The 1.8m swell and offshore wind could be alright, if you enjoy a side of windburn with your wipeouts.

🌊 Swell: 1.8m @ 12s
💨 Wind: 34.0km/h SW (OFFSHORE)
💨 Gusts: 54.0km/h
🌊 Wind waves: 1.1m

📋 Clean conditions with offshore wind</desc>
    <icon src="https://raw.githubusercontent.com/OiErU/weather-dashboard/main/posters/lagide_poster.jpg" />
  </programme>
  <programme start="20260218180000 +0000" stop="20260219000000 +0000" channel="ericeira-surfline">
    <title lang="en">🌊 1.9m @ 11s ONSHORE</title>
    <desc lang="en">With 1.9m of onshore slop, today's session offers a vigorous workout in turbulent conditions.

🌊 Swell: 1.9m @ 11s
💨 Wind: 19.0km/h WNW (ONSHORE)
💨 Gusts: 50.0km/h
🌊 Wind waves: 0.9m</desc>
    <icon src="https://raw.githubusercontent.com/OiErU/weather-dashboard/main/posters/ericeira_poster.jpg" />
  </programme>
  <programme start="20260218180000 +0000" stop="20260219000000 +0000" channel="ericeira-meo">
    <title lang="en">🌊 1.9m @ 11s ONSHORE</title>
    <desc lang="en">With 1.9m of onshore slop, today's session offers a vigorous workout in turbulent conditions.

🌊 Swell: 1.9m @ 11s
💨 Wind: 19.0km/h WNW (ONSHORE)
💨 Gusts: 50.0km/h
🌊 Wind waves: 0.9m</desc>
    <icon src="https://raw.githubusercontent.com/OiErU/weather-dashboard/main/posters/ericeira_poster.jpg" />
  </programme>
  <programme start="20260218180000 +0000" stop="20260219000000 +0000" channel="supertubos-surfline">
    <title lang="en">🌊 2.3m @ 11s CROSS</title>
    <desc lang="en">With that 2.3m swell and onshore wind, today will likely be a good day to watch the waves close out from the beach.

🌊 Swell: 2.3m @ 11s
💨 Wind: 22.0km/h WNW (CROSS)
💨 Gusts: 36.0km/h
🌊 Wind waves: 0.9m</desc>
    <icon src="https://raw.githubusercontent.com/OiErU/weather-dashboard/main/posters/supertubos_poster.jpg" />
  </programme>
  <programme start="20260218180000 +0000" stop="20260219000000 +0000" channel="supertubos-meo">
    <title lang="en">🌊 2.3m @ 11s CROSS</title>
    <desc lang="en">With that 2.3m swell and onshore wind, today will likely be a good day to watch the waves close out from the beach.

🌊 Swell: 2.3m @ 11s
💨 Wind: 22.0km/h WNW (CROSS)
💨 Gusts: 36.0km/h
🌊 Wind waves: 0.9m</desc>
    <icon src="https://raw.githubusercontent.com/OiErU/weather-dashboard/main/posters/supertubos_poster.jpg" />
  </programme>
  <programme start="20260218180000 +0000" stop="20260219000000 +0000" channel="molheleste-surfline">
    <title lang="en">💨 2.3m @ 11s ONSHORE</title>
    <desc lang="en">The 2.3m windswell will offer some… exercise, if you enjoy paddling into closeouts.

🌊 Swell: 2.3m @ 11s
💨 Wind: 22.0km/h WNW (ONSHORE)
💨 Gusts: 36.0km/h
🌊 Wind waves: 0.9m

📋 Onshore wind making it messy</desc>
    <icon src="https://raw.githubusercontent.com/OiErU/weather-dashboard/main/posters/molheleste_poster.jpg" />
  </programme>
  <programme start="20260218180000 +0000" stop="20260219000000 +0000" channel="molheleste-meo">
    <title lang="en">💨 2.3m @ 11s ONSHORE</title>
    <desc lang="en">The 2.3m windswell will offer some… exercise, if you enjoy paddling into closeouts.

🌊 Swell: 2.3m @ 11s
💨 Wind: 22.0km/h WNW (ONSHORE)
💨 Gusts: 36.0km/h
🌊 Wind waves: 0.9m

📋 Onshore wind making it messy</desc>
    <icon src="https://raw.githubusercontent.com/OiErU/weather-dashboard/main/posters/molheleste_poster.jpg" />
  </programme>
  <programme start="20260218180000 +0000" stop="20260219000000 +0000" channel="baia-meo">
    <title lang="en">💨 2.3m @ 11s ONSHORE</title>
    <desc lang="en">With 2.3m of onshore slop, today's session looks more like a washing machine simulator.

🌊 Swell: 2.3m @ 11s
💨 Wind: 22.0km/h WNW (ONSHORE)
💨 Gusts: 36.0km/h
🌊 Wind waves: 0.9m

📋 Onshore wind making it messy</desc>
    <icon src="https://raw.githubusercontent.com/OiErU/weather-dashboard/main/posters/baleal_poster.jpg" />
  </programme>
  <programme start="20260218180000 +0000" stop="20260219000000 +0000" channel="cantinho-surfline">
    <title lang="en">💨 2.3m @ 11s ONSHORE</title>
    <desc lang="en">With 2.3m of onshore slop, today's Cantinho session sounds like a good way to get tumbled.

🌊 Swell: 2.3m @ 11s
💨 Wind: 22.0km/h WNW (ONSHORE)
💨 Gusts: 36.0km/h
🌊 Wind waves: 0.9m

📋 Onshore wind making it messy</desc>
    <icon src="https://raw.githubusercontent.com/OiErU/weather-dashboard/main/posters/cantinho_poster.jpg" />
  </programme>
  <programme start="20260218180000 +0000" stop="20260219000000 +0000" channel="cantinho-meo">
    <title lang="en">💨 2.3m @ 11s ONSHORE</title>
    <desc lang="en">With 2.3m of onshore slop, today's Cantinho session sounds like a good way to get tumbled.

🌊 Swell: 2.3m @ 11s
💨 Wind: 22.0km/h WNW (ONSHORE)
💨 Gusts: 36.0km/h
🌊 Wind waves: 0.9m

📋 Onshore wind making it messy</desc>
    <icon src="https://raw.githubusercontent.com/OiErU/weather-dashboard/main/posters/cantinho_poster.jpg" />
  </programme>
  <programme start="20260218180000 +0000" stop="20260219000000 +0000" channel="baleal-surfline">
    <title lang="en">🌊 2.3m @ 11s CROSS</title>
    <desc lang="en">The 2.3 meter swell and crosswind suggest more of a tumble in the washing machine than a ride today.

🌊 Swell: 2.3m @ 11s
💨 Wind: 22.0km/h WNW (CROSS)
💨 Gusts: 36.0km/h
🌊 Wind waves: 0.9m</desc>
    <icon src="https://raw.githubusercontent.com/OiErU/weather-dashboard/main/posters/baleal_poster.jpg" />
  </programme>
  <programme start="20260218180000 +0000" stop="20260219000000 +0000" channel="lagide-surfline">
    <title lang="en">🌊 2.3m @ 11s CROSS</title>
    <desc lang="en">With 2.3m of swell and that wind, today's session promises a thorough beating.

🌊 Swell: 2.3m @ 11s
💨 Wind: 22.0km/h WNW (CROSS)
💨 Gusts: 36.0km/h
🌊 Wind waves: 0.9m</desc>
    <icon src="https://raw.githubusercontent.com/OiErU/weather-dashboard/main/posters/lagide_poster.jpg" />
  </programme>
  <programme start="20260218180000 +0000" stop="20260219000000 +0000" channel="lagide-meo">
    <title lang="en">🌊 2.3m @ 11s CROSS</title>
    <desc lang="en">With 2.3m of swell and that wind, today's session promises a thorough beating.

🌊 Swell: 2.3m @ 11s
💨 Wind: 22.0km/h WNW (CROSS)
💨 Gusts: 36.0km/h
🌊 Wind waves: 0.9m</desc>
    <icon src="https://raw.githubusercontent.com/OiErU/weather-dashboard/main/posters/lagide_poster.jpg" />
  </programme>
</tv>