<?xml version='1.0' encoding='utf-8'?>
<tv generator-info-name="Surf EPG (Open-Meteo)" generator-info-url="https://raw.githubusercontent.com/OiErU/weather-dashboard/main">
  <channel id="ericeira-surfline">
    <display-name>Surfline Ericeira</display-name>
    <icon src="https://raw.githubusercontent.com/OiErU/weather-dashboard/main/logos/ericeira.png?v=2" />
  </channel>
  <channel id="ericeira-meo">
    <display-name>MEO Ericeira</display-name>
    <icon src="https://raw.githubusercontent.com/OiErU/weather-dashboard/main/logos/ericeira.png?v=2" />
  </channel>
  <channel id="supertubos-surfline">
    <display-name>Surfline Supertubos</display-name>
    <icon src="https://raw.githubusercontent.com/OiErU/weather-dashboard/main/logos/supertubos.png?v=2" />
  </channel>
  <channel id="supertubos-meo">
    <display-name>MEO Supertubos</display-name>
    <icon src="https://raw.githubusercontent.com/OiErU/weather-dashboard/main/logos/supertubos.png?v=2" />
  </channel>
  <channel id="molheleste-surfline">
    <display-name>Surfline Molhe Leste</display-name>
    <icon src="https://raw.githubusercontent.com/OiErU/weather-dashboard/main/logos/molheleste.png?v=2" />
  </channel>
  <channel id="molheleste-meo">
    <display-name>MEO Molhe Leste</display-name>
    <icon src="https://raw.githubusercontent.com/OiErU/weather-dashboard/main/logos/molheleste.png?v=2" />
  </channel>
  <channel id="baia-meo">
    <display-name>MEO Baia</display-name>
    <icon src="https://raw.githubusercontent.com/OiErU/weather-dashboard/main/logos/baleal.png?v=2" />
  </channel>
  <channel id="cantinho-surfline">
    <display-name>Surfline Cantinho</display-name>
    <icon src="https://raw.githubusercontent.com/OiErU/weather-dashboard/main/logos/cantinho.png?v=2" />
  </channel>
  <channel id="cantinho-meo">
    <display-name>MEO Cantinho</display-name>
    <icon src="https://raw.githubusercontent.com/OiErU/weather-dashboard/main/logos/cantinho.png?v=2" />
  </channel>
  <channel id="baleal-surfline">
    <display-name>Surfline Baleal</display-name>
    <icon src="https://raw.githubusercontent.com/OiErU/weather-dashboard/main/logos/baleal.png?v=2" />
  </channel>
  <channel id="lagide-surfline">
    <display-name>Surfline Lagide</display-name>
    <icon src="https://raw.githubusercontent.com/OiErU/weather-dashboard/main/logos/lagide.png?v=2" />
  </channel>
  <channel id="lagide-meo">
    <display-name>MEO Lagide</display-name>
    <icon src="https://raw.githubusercontent.com/OiErU/weather-dashboard/main/logos/lagide.png?v=2" />
  </channel>
  <programme start="20260413000000 +0000" stop="20260413060000 +0000" channel="ericeira-surfline">
    <title lang="en">⚠️ 4.3m @ 15s CROSS</title>
    <desc lang="en">At nearly 4.5m, and with that wind, Ribeira's offering lessons in humility today.

🌊 Swell: 4.3m @ 15s
💨 Wind: 14.0km/h NNW (CROSS)
💨 Gusts: 33.0km/h
🌊 Wind waves: 1.6m

📋 Very large swell - experienced surfers only • Long period - powerful waves • Significant wind chop</desc>
    <icon src="https://raw.githubusercontent.com/OiErU/weather-dashboard/main/posters/ericeira_poster.jpg" />
  </programme>
  <programme start="20260413000000 +0000" stop="20260413060000 +0000" channel="ericeira-meo">
    <title lang="en">⚠️ 4.3m @ 15s CROSS</title>
    <desc lang="en">At nearly 4.5m, and with that wind, Ribeira's offering lessons in humility today.

🌊 Swell: 4.3m @ 15s
💨 Wind: 14.0km/h NNW (CROSS)
💨 Gusts: 33.0km/h
🌊 Wind waves: 1.6m

📋 Very large swell - experienced surfers only • Long period - powerful waves • Significant wind chop</desc>
    <icon src="https://raw.githubusercontent.com/OiErU/weather-dashboard/main/posters/ericeira_poster.jpg" />
  </programme>
  <programme start="20260413000000 +0000" stop="20260413060000 +0000" channel="supertubos-surfline">
    <title lang="en">⚠️ 4.1m @ 15s CROSS</title>
    <desc lang="en">At 4.1m with that wind, Supertubos is best observed from a safe distance today.

🌊 Swell: 4.1m @ 15s
💨 Wind: 22.0km/h NNW (CROSS)
💨 Gusts: 39.0km/h
🌊 Wind waves: 1.4m

📋 Very large swell - experienced surfers only • Long period - powerful waves • Significant wind chop</desc>
    <icon src="https://raw.githubusercontent.com/OiErU/weather-dashboard/main/posters/supertubos_poster.jpg" />
  </programme>
  <programme start="20260413000000 +0000" stop="20260413060000 +0000" channel="supertubos-meo">
    <title lang="en">⚠️ 4.1m @ 15s CROSS</title>
    <desc lang="en">At 4.1m with that wind, Supertubos is best observed from a safe distance today.

🌊 Swell: 4.1m @ 15s
💨 Wind: 22.0km/h NNW (CROSS)
💨 Gusts: 39.0km/h
🌊 Wind waves: 1.4m

📋 Very large swell - experienced surfers only • Long period - powerful waves • Significant wind chop</desc>
    <icon src="https://raw.githubusercontent.com/OiErU/weather-dashboard/main/posters/supertubos_poster.jpg" />
  </programme>
  <programme start="20260413000000 +0000" stop="20260413060000 +0000" channel="molheleste-surfline">
    <title lang="en">⚠️ 4.1m @ 15s CROSS</title>
    <desc lang="en">With a 4.1m swell and that wind, Molhe Leste will be closing out impressively today.

🌊 Swell: 4.1m @ 15s
💨 Wind: 22.0km/h NNW (CROSS)
💨 Gusts: 39.0km/h
🌊 Wind waves: 1.4m

📋 Very large swell - experienced surfers only • Long period - powerful waves • Significant wind chop</desc>
    <icon src="https://raw.githubusercontent.com/OiErU/weather-dashboard/main/posters/molheleste_poster.jpg" />
  </programme>
  <programme start="20260413000000 +0000" stop="20260413060000 +0000" channel="molheleste-meo">
    <title lang="en">⚠️ 4.1m @ 15s CROSS</title>
    <desc lang="en">With a 4.1m swell and that wind, Molhe Leste will be closing out impressively today.

🌊 Swell: 4.1m @ 15s
💨 Wind: 22.0km/h NNW (CROSS)
💨 Gusts: 39.0km/h
🌊 Wind waves: 1.4m

📋 Very large swell - experienced surfers only • Long period - powerful waves • Significant wind chop</desc>
    <icon src="https://raw.githubusercontent.com/OiErU/weather-dashboard/main/posters/molheleste_poster.jpg" />
  </programme>
  <programme start="20260413000000 +0000" stop="20260413060000 +0000" channel="baia-meo">
    <title lang="en">💨 4.1m @ 15s ONSHORE</title>
    <desc lang="en">With that 4.1m of swell and onshore wind, today Meio da Baia will be a washing machine best observed from the café.

🌊 Swell: 4.1m @ 15s
💨 Wind: 22.0km/h NNW (ONSHORE)
💨 Gusts: 39.0km/h
🌊 Wind waves: 1.4m

📋 Very large swell - experienced surfers only • Onshore wind making it messy • Long period - powerful waves • Significant wind chop</desc>
    <icon src="https://raw.githubusercontent.com/OiErU/weather-dashboard/main/posters/baleal_poster.jpg" />
  </programme>
  <programme start="20260413000000 +0000" stop="20260413060000 +0000" channel="cantinho-surfline">
    <title lang="en">💨 4.1m @ 15s ONSHORE</title>
    <desc lang="en">With a 4.1m swell and onshore wind, today's session will mainly involve getting washed up on the beach.

🌊 Swell: 4.1m @ 15s
💨 Wind: 22.0km/h NNW (ONSHORE)
💨 Gusts: 39.0km/h
🌊 Wind waves: 1.4m

📋 Very large swell - experienced surfers only • Onshore wind making it messy • Long period - powerful waves • Significant wind chop</desc>
    <icon src="https://raw.githubusercontent.com/OiErU/weather-dashboard/main/posters/cantinho_poster.jpg" />
  </programme>
  <programme start="20260413000000 +0000" stop="20260413060000 +0000" channel="cantinho-meo">
    <title lang="en">💨 4.1m @ 15s ONSHORE</title>
    <desc lang="en">With a 4.1m swell and onshore wind, today's session will mainly involve getting washed up on the beach.

🌊 Swell: 4.1m @ 15s
💨 Wind: 22.0km/h NNW (ONSHORE)
💨 Gusts: 39.0km/h
🌊 Wind waves: 1.4m

📋 Very large swell - experienced surfers only • Onshore wind making it messy • Long period - powerful waves • Significant wind chop</desc>
    <icon src="https://raw.githubusercontent.com/OiErU/weather-dashboard/main/posters/cantinho_poster.jpg" />
  </programme>
  <programme start="20260413000000 +0000" stop="20260413060000 +0000" channel="baleal-surfline">
    <title lang="en">💨 4.1m @ 15s ONSHORE</title>
    <desc lang="en">With a 4.1m swell and onshore wind, today's Baleal Norte promises a churning, closeout-fueled body slam.

🌊 Swell: 4.1m @ 15s
💨 Wind: 22.0km/h NNW (ONSHORE)
💨 Gusts: 39.0km/h
🌊 Wind waves: 1.4m

📋 Very large swell - experienced surfers only • Onshore wind making it messy • Long period - powerful waves • Significant wind chop</desc>
    <icon src="https://raw.githubusercontent.com/OiErU/weather-dashboard/main/posters/baleal_poster.jpg" />
  </programme>
  <programme start="20260413000000 +0000" stop="20260413060000 +0000" channel="lagide-surfline">
    <title lang="en">💨 4.1m @ 15s ONSHORE</title>
    <desc lang="en">At 4.1 meters with that wind, today's session will mostly involve getting sandblasted.

🌊 Swell: 4.1m @ 15s
💨 Wind: 22.0km/h NNW (ONSHORE)
💨 Gusts: 39.0km/h
🌊 Wind waves: 1.4m

📋 Very large swell - experienced surfers only • Onshore wind making it messy • Long period - powerful waves • Significant wind chop</desc>
    <icon src="https://raw.githubusercontent.com/OiErU/weather-dashboard/main/posters/lagide_poster.jpg" />
  </programme>
  <programme start="20260413000000 +0000" stop="20260413060000 +0000" channel="lagide-meo">
    <title lang="en">💨 4.1m @ 15s ONSHORE</title>
    <desc lang="en">At 4.1 meters with that wind, today's session will mostly involve getting sandblasted.

🌊 Swell: 4.1m @ 15s
💨 Wind: 22.0km/h NNW (ONSHORE)
💨 Gusts: 39.0km/h
🌊 Wind waves: 1.4m

📋 Very large swell - experienced surfers only • Onshore wind making it messy • Long period - powerful waves • Significant wind chop</desc>
    <icon src="https://raw.githubusercontent.com/OiErU/weather-dashboard/main/posters/lagide_poster.jpg" />
  </programme>
  <programme start="20260413060000 +0000" stop="20260413120000 +0000" channel="ericeira-surfline">
    <title lang="en">🌊 3.9m @ 15s CROSS</title>
    <desc lang="en">At nearly four meters, the sets will be interesting today; just how interesting remains to be seen.

🌊 Swell: 3.9m @ 15s
💨 Wind: 9.0km/h NW (CROSS)
💨 Gusts: 22.0km/h
🌊 Wind waves: 0.6m

📋 Long period - powerful waves</desc>
    <icon src="https://raw.githubusercontent.com/OiErU/weather-dashboard/main/posters/ericeira_poster.jpg" />
  </programme>
  <programme start="20260413060000 +0000" stop="20260413120000 +0000" channel="ericeira-meo">
    <title lang="en">🌊 3.9m @ 15s CROSS</title>
    <desc lang="en">At nearly four meters, the sets will be interesting today; just how interesting remains to be seen.

🌊 Swell: 3.9m @ 15s
💨 Wind: 9.0km/h NW (CROSS)
💨 Gusts: 22.0km/h
🌊 Wind waves: 0.6m

📋 Long period - powerful waves</desc>
    <icon src="https://raw.githubusercontent.com/OiErU/weather-dashboard/main/posters/ericeira_poster.jpg" />
  </programme>
  <programme start="20260413060000 +0000" stop="20260413120000 +0000" channel="supertubos-surfline">
    <title lang="en">🌊 3.7m @ 15s CROSS</title>
    <desc lang="en">At nearly 4m, it'll be a closeout lottery out there today, with a good chance of sand in places it shouldn't be.

🌊 Swell: 3.7m @ 15s
💨 Wind: 12.0km/h NW (CROSS)
💨 Gusts: 24.0km/h
🌊 Wind waves: 0.5m

📋 Long period - powerful waves</desc>
    <icon src="https://raw.githubusercontent.com/OiErU/weather-dashboard/main/posters/supertubos_poster.jpg" />
  </programme>
  <programme start="20260413060000 +0000" stop="20260413120000 +0000" channel="supertubos-meo">
    <title lang="en">🌊 3.7m @ 15s CROSS</title>
    <desc lang="en">At nearly 4m, it'll be a closeout lottery out there today, with a good chance of sand in places it shouldn't be.

🌊 Swell: 3.7m @ 15s
💨 Wind: 12.0km/h NW (CROSS)
💨 Gusts: 24.0km/h
🌊 Wind waves: 0.5m

📋 Long period - powerful waves</desc>
    <icon src="https://raw.githubusercontent.com/OiErU/weather-dashboard/main/posters/supertubos_poster.jpg" />
  </programme>
  <programme start="20260413060000 +0000" stop="20260413120000 +0000" channel="molheleste-surfline">
    <title lang="en">🌊 3.7m @ 15s CROSS</title>
    <desc lang="en">At 3.7m with that wind, today's less a bodyboarding session, more a survival exercise.

🌊 Swell: 3.7m @ 15s
💨 Wind: 12.0km/h NW (CROSS)
💨 Gusts: 24.0km/h
🌊 Wind waves: 0.5m

📋 Long period - powerful waves</desc>
    <icon src="https://raw.githubusercontent.com/OiErU/weather-dashboard/main/posters/molheleste_poster.jpg" />
  </programme>
  <programme start="20260413060000 +0000" stop="20260413120000 +0000" channel="molheleste-meo">
    <title lang="en">🌊 3.7m @ 15s CROSS</title>
    <desc lang="en">At 3.7m with that wind, today's less a bodyboarding session, more a survival exercise.

🌊 Swell: 3.7m @ 15s
💨 Wind: 12.0km/h NW (CROSS)
💨 Gusts: 24.0km/h
🌊 Wind waves: 0.5m

📋 Long period - powerful waves</desc>
    <icon src="https://raw.githubusercontent.com/OiErU/weather-dashboard/main/posters/molheleste_poster.jpg" />
  </programme>
  <programme start="20260413060000 +0000" stop="20260413120000 +0000" channel="baia-meo">
    <title lang="en">🌊 3.7m @ 15s ONSHORE</title>
    <desc lang="en">At 3.7 meters with that onshore breeze, today's session will mainly involve getting sandblasted in the shorebreak.

🌊 Swell: 3.7m @ 15s
💨 Wind: 12.0km/h NW (ONSHORE)
💨 Gusts: 24.0km/h
🌊 Wind waves: 0.5m

📋 Long period - powerful waves</desc>
    <icon src="https://raw.githubusercontent.com/OiErU/weather-dashboard/main/posters/baleal_poster.jpg" />
  </programme>
  <programme start="20260413060000 +0000" stop="20260413120000 +0000" channel="cantinho-surfline">
    <title lang="en">🌊 3.7m @ 15s ONSHORE</title>
    <desc lang="en">With 3.7 meters and onshore wind, today's session will mostly involve getting pummeled and finding lost fins.

🌊 Swell: 3.7m @ 15s
💨 Wind: 12.0km/h NW (ONSHORE)
💨 Gusts: 24.0km/h
🌊 Wind waves: 0.5m

📋 Long period - powerful waves</desc>
    <icon src="https://raw.githubusercontent.com/OiErU/weather-dashboard/main/posters/cantinho_poster.jpg" />
  </programme>
  <programme start="20260413060000 +0000" stop="20260413120000 +0000" channel="cantinho-meo">
    <title lang="en">🌊 3.7m @ 15s ONSHORE</title>
    <desc lang="en">With 3.7 meters and onshore wind, today's session will mostly involve getting pummeled and finding lost fins.

🌊 Swell: 3.7m @ 15s
💨 Wind: 12.0km/h NW (ONSHORE)
💨 Gusts: 24.0km/h
🌊 Wind waves: 0.5m

📋 Long period - powerful waves</desc>
    <icon src="https://raw.githubusercontent.com/OiErU/weather-dashboard/main/posters/cantinho_poster.jpg" />
  </programme>
  <programme start="20260413060000 +0000" stop="20260413120000 +0000" channel="baleal-surfline">
    <title lang="en">🌊 3.7m @ 15s ONSHORE</title>
    <desc lang="en">That 3.7m swell and onshore wind suggests a closeout party, unless you enjoy getting tumbled like laundry.

🌊 Swell: 3.7m @ 15s
💨 Wind: 12.0km/h NW (ONSHORE)
💨 Gusts: 24.0km/h
🌊 Wind waves: 0.5m

📋 Long period - powerful waves</desc>
    <icon src="https://raw.githubusercontent.com/OiErU/weather-dashboard/main/posters/baleal_poster.jpg" />
  </programme>
  <programme start="20260413060000 +0000" stop="20260413120000 +0000" channel="lagide-surfline">
    <title lang="en">🌊 3.7m @ 15s ONSHORE</title>
    <desc lang="en">Three-point-seven meters with onshore wind? Sounds like a good day to watch someone else get pounded.

🌊 Swell: 3.7m @ 15s
💨 Wind: 12.0km/h NW (ONSHORE)
💨 Gusts: 24.0km/h
🌊 Wind waves: 0.5m

📋 Long period - powerful waves</desc>
    <icon src="https://raw.githubusercontent.com/OiErU/weather-dashboard/main/posters/lagide_poster.jpg" />
  </programme>
  <programme start="20260413060000 +0000" stop="20260413120000 +0000" channel="lagide-meo">
    <title lang="en">🌊 3.7m @ 15s ONSHORE</title>
    <desc lang="en">Three-point-seven meters with onshore wind? Sounds like a good day to watch someone else get pounded.

🌊 Swell: 3.7m @ 15s
💨 Wind: 12.0km/h NW (ONSHORE)
💨 Gusts: 24.0km/h
🌊 Wind waves: 0.5m

📋 Long period - powerful waves</desc>
    <icon src="https://raw.githubusercontent.com/OiErU/weather-dashboard/main/posters/lagide_poster.jpg" />
  </programme>
  <programme start="20260413120000 +0000" stop="20260413180000 +0000" channel="ericeira-surfline">
    <title lang="en">🌊 3.5m @ 15s ONSHORE</title>
    <desc lang="en">With 3.5 meters and onshore wind, today will be a character-building experience, mostly spent underwater.

🌊 Swell: 3.5m @ 15s
💨 Wind: 16.0km/h NW (ONSHORE)
💨 Gusts: 35.0km/h
🌊 Wind waves: 0.5m

📋 Long period - powerful waves</desc>
    <icon src="https://raw.githubusercontent.com/OiErU/weather-dashboard/main/posters/ericeira_poster.jpg" />
  </programme>
  <programme start="20260413120000 +0000" stop="20260413180000 +0000" channel="ericeira-meo">
    <title lang="en">🌊 3.5m @ 15s ONSHORE</title>
    <desc lang="en">With 3.5 meters and onshore wind, today will be a character-building experience, mostly spent underwater.

🌊 Swell: 3.5m @ 15s
💨 Wind: 16.0km/h NW (ONSHORE)
💨 Gusts: 35.0km/h
🌊 Wind waves: 0.5m

📋 Long period - powerful waves</desc>
    <icon src="https://raw.githubusercontent.com/OiErU/weather-dashboard/main/posters/ericeira_poster.jpg" />
  </programme>
  <programme start="20260413120000 +0000" stop="20260413180000 +0000" channel="supertubos-surfline">
    <title lang="en">🌊 3.3m @ 15s CROSS</title>
    <desc lang="en">With 3.3 meters and onshore wind, today's Supertubos might just rearrange your face.

🌊 Swell: 3.3m @ 15s
💨 Wind: 19.0km/h WNW (CROSS)
💨 Gusts: 32.0km/h
🌊 Wind waves: 0.4m

📋 Long period - powerful waves</desc>
    <icon src="https://raw.githubusercontent.com/OiErU/weather-dashboard/main/posters/supertubos_poster.jpg" />
  </programme>
  <programme start="20260413120000 +0000" stop="20260413180000 +0000" channel="supertubos-meo">
    <title lang="en">🌊 3.3m @ 15s CROSS</title>
    <desc lang="en">With 3.3 meters and onshore wind, today's Supertubos might just rearrange your face.

🌊 Swell: 3.3m @ 15s
💨 Wind: 19.0km/h WNW (CROSS)
💨 Gusts: 32.0km/h
🌊 Wind waves: 0.4m

📋 Long period - powerful waves</desc>
    <icon src="https://raw.githubusercontent.com/OiErU/weather-dashboard/main/posters/supertubos_poster.jpg" />
  </programme>
  <programme start="20260413120000 +0000" stop="20260413180000 +0000" channel="molheleste-surfline">
    <title lang="en">🌊 3.3m @ 15s ONSHORE</title>
    <desc lang="en">With that onshore wind fighting a 3.3m swell, today will be a masterclass in survival swimming.

🌊 Swell: 3.3m @ 15s
💨 Wind: 19.0km/h WNW (ONSHORE)
💨 Gusts: 32.0km/h
🌊 Wind waves: 0.4m

📋 Long period - powerful waves</desc>
    <icon src="https://raw.githubusercontent.com/OiErU/weather-dashboard/main/posters/molheleste_poster.jpg" />
  </programme>
  <programme start="20260413120000 +0000" stop="20260413180000 +0000" channel="molheleste-meo">
    <title lang="en">🌊 3.3m @ 15s ONSHORE</title>
    <desc lang="en">With that onshore wind fighting a 3.3m swell, today will be a masterclass in survival swimming.

🌊 Swell: 3.3m @ 15s
💨 Wind: 19.0km/h WNW (ONSHORE)
💨 Gusts: 32.0km/h
🌊 Wind waves: 0.4m

📋 Long period - powerful waves</desc>
    <icon src="https://raw.githubusercontent.com/OiErU/weather-dashboard/main/posters/molheleste_poster.jpg" />
  </programme>
  <programme start="20260413120000 +0000" stop="20260413180000 +0000" channel="baia-meo">
    <title lang="en">🌊 3.3m @ 15s ONSHORE</title>
    <desc lang="en">With a 3.3m swell and onshore wind, today's session will be mostly a vigorous swim.

🌊 Swell: 3.3m @ 15s
💨 Wind: 19.0km/h WNW (ONSHORE)
💨 Gusts: 32.0km/h
🌊 Wind waves: 0.4m

📋 Long period - powerful waves</desc>
    <icon src="https://raw.githubusercontent.com/OiErU/weather-dashboard/main/posters/baleal_poster.jpg" />
  </programme>
  <programme start="20260413120000 +0000" stop="20260413180000 +0000" channel="cantinho-surfline">
    <title lang="en">🌊 3.3m @ 15s ONSHORE</title>
    <desc lang="en">With that onshore breeze and 3.3m swell, today's session will be an excellent test of one's duck diving and frustration tolerance.

🌊 Swell: 3.3m @ 15s
💨 Wind: 19.0km/h WNW (ONSHORE)
💨 Gusts: 32.0km/h
🌊 Wind waves: 0.4m

📋 Long period - powerful waves</desc>
    <icon src="https://raw.githubusercontent.com/OiErU/weather-dashboard/main/posters/cantinho_poster.jpg" />
  </programme>
  <programme start="20260413120000 +0000" stop="20260413180000 +0000" channel="cantinho-meo">
    <title lang="en">🌊 3.3m @ 15s ONSHORE</title>
    <desc lang="en">With that onshore breeze and 3.3m swell, today's session will be an excellent test of one's duck diving and frustration tolerance.

🌊 Swell: 3.3m @ 15s
💨 Wind: 19.0km/h WNW (ONSHORE)
💨 Gusts: 32.0km/h
🌊 Wind waves: 0.4m

📋 Long period - powerful waves</desc>
    <icon src="https://raw.githubusercontent.com/OiErU/weather-dashboard/main/posters/cantinho_poster.jpg" />
  </programme>
  <programme start="20260413120000 +0000" stop="20260413180000 +0000" channel="baleal-surfline">
    <title lang="en">🌊 3.3m @ 15s CROSS</title>
    <desc lang="en">With that period and onshore wind, those 3.3m waves will be closing out messily across the beach.

🌊 Swell: 3.3m @ 15s
💨 Wind: 19.0km/h WNW (CROSS)
💨 Gusts: 32.0km/h
🌊 Wind waves: 0.4m

📋 Long period - powerful waves</desc>
    <icon src="https://raw.githubusercontent.com/OiErU/weather-dashboard/main/posters/baleal_poster.jpg" />
  </programme>
  <programme start="20260413120000 +0000" stop="20260413180000 +0000" channel="lagide-surfline">
    <title lang="en">🌊 3.3m @ 15s CROSS</title>
    <desc lang="en">Three-metre-plus Lagide with that wind; mostly getting pounded today, I reckon.

🌊 Swell: 3.3m @ 15s
💨 Wind: 19.0km/h WNW (CROSS)
💨 Gusts: 32.0km/h
🌊 Wind waves: 0.4m

📋 Long period - powerful waves</desc>
    <icon src="https://raw.githubusercontent.com/OiErU/weather-dashboard/main/posters/lagide_poster.jpg" />
  </programme>
  <programme start="20260413120000 +0000" stop="20260413180000 +0000" channel="lagide-meo">
    <title lang="en">🌊 3.3m @ 15s CROSS</title>
    <desc lang="en">Three-metre-plus Lagide with that wind; mostly getting pounded today, I reckon.

🌊 Swell: 3.3m @ 15s
💨 Wind: 19.0km/h WNW (CROSS)
💨 Gusts: 32.0km/h
🌊 Wind waves: 0.4m

📋 Long period - powerful waves</desc>
    <icon src="https://raw.githubusercontent.com/OiErU/weather-dashboard/main/posters/lagide_poster.jpg" />
  </programme>
  <programme start="20260413180000 +0000" stop="20260414000000 +0000" channel="ericeira-surfline">
    <title lang="en">🌊 3.1m @ 14s ONSHORE</title>
    <desc lang="en">With that onshore wind and 3-meter swell, you might get a pounding today, or a good laugh trying.

🌊 Swell: 3.1m @ 14s
💨 Wind: 16.0km/h WNW (ONSHORE)
💨 Gusts: 35.0km/h
🌊 Wind waves: 0.4m</desc>
    <icon src="https://raw.githubusercontent.com/OiErU/weather-dashboard/main/posters/ericeira_poster.jpg" />
  </programme>
  <programme start="20260413180000 +0000" stop="20260414000000 +0000" channel="ericeira-meo">
    <title lang="en">🌊 3.1m @ 14s ONSHORE</title>
    <desc lang="en">With that onshore wind and 3-meter swell, you might get a pounding today, or a good laugh trying.

🌊 Swell: 3.1m @ 14s
💨 Wind: 16.0km/h WNW (ONSHORE)
💨 Gusts: 35.0km/h
🌊 Wind waves: 0.4m</desc>
    <icon src="https://raw.githubusercontent.com/OiErU/weather-dashboard/main/posters/ericeira_poster.jpg" />
  </programme>
  <programme start="20260413180000 +0000" stop="20260414000000 +0000" channel="supertubos-surfline">
    <title lang="en">🌊 2.9m @ 14s CROSS</title>
    <desc lang="en">With a 2.9m swell and that wind, today's Supertubos will offer exciting, if somewhat chaotic, closeout practice.

🌊 Swell: 2.9m @ 14s
💨 Wind: 16.0km/h W (CROSS)
💨 Gusts: 27.0km/h
🌊 Wind waves: 0.4m</desc>
    <icon src="https://raw.githubusercontent.com/OiErU/weather-dashboard/main/posters/supertubos_poster.jpg" />
  </programme>
  <programme start="20260413180000 +0000" stop="20260414000000 +0000" channel="supertubos-meo">
    <title lang="en">🌊 2.9m @ 14s CROSS</title>
    <desc lang="en">With a 2.9m swell and that wind, today's Supertubos will offer exciting, if somewhat chaotic, closeout practice.

🌊 Swell: 2.9m @ 14s
💨 Wind: 16.0km/h W (CROSS)
💨 Gusts: 27.0km/h
🌊 Wind waves: 0.4m</desc>
    <icon src="https://raw.githubusercontent.com/OiErU/weather-dashboard/main/posters/supertubos_poster.jpg" />
  </programme>
  <programme start="20260413180000 +0000" stop="20260414000000 +0000" channel="molheleste-surfline">
    <title lang="en">🌊 2.9m @ 14s ONSHORE</title>
    <desc lang="en">With 2.9m of onshore slop, it'll be character building, assuming you enjoy eating sand.

🌊 Swell: 2.9m @ 14s
💨 Wind: 16.0km/h W (ONSHORE)
💨 Gusts: 27.0km/h
🌊 Wind waves: 0.4m</desc>
    <icon src="https://raw.githubusercontent.com/OiErU/weather-dashboard/main/posters/molheleste_poster.jpg" />
  </programme>
  <programme start="20260413180000 +0000" stop="20260414000000 +0000" channel="molheleste-meo">
    <title lang="en">🌊 2.9m @ 14s ONSHORE</title>
    <desc lang="en">With 2.9m of onshore slop, it'll be character building, assuming you enjoy eating sand.

🌊 Swell: 2.9m @ 14s
💨 Wind: 16.0km/h W (ONSHORE)
💨 Gusts: 27.0km/h
🌊 Wind waves: 0.4m</desc>
    <icon src="https://raw.githubusercontent.com/OiErU/weather-dashboard/main/posters/molheleste_poster.jpg" />
  </programme>
  <programme start="20260413180000 +0000" stop="20260414000000 +0000" channel="baia-meo">
    <title lang="en">🌊 2.9m @ 14s ONSHORE</title>
    <desc lang="en">2.9 meters and onshore wind? Might be good for practicing duck diving into whitewater today.

🌊 Swell: 2.9m @ 14s
💨 Wind: 16.0km/h W (ONSHORE)
💨 Gusts: 27.0km/h
🌊 Wind waves: 0.4m</desc>
    <icon src="https://raw.githubusercontent.com/OiErU/weather-dashboard/main/posters/baleal_poster.jpg" />
  </programme>
  <programme start="20260413180000 +0000" stop="20260414000000 +0000" channel="cantinho-surfline">
    <title lang="en">🌊 2.9m @ 14s ONSHORE</title>
    <desc lang="en">With that onshore wind and nearly 3-meter swell, today's Cantinho session sounds like a good way to get sandblasted.

🌊 Swell: 2.9m @ 14s
💨 Wind: 16.0km/h W (ONSHORE)
💨 Gusts: 27.0km/h
🌊 Wind waves: 0.4m</desc>
    <icon src="https://raw.githubusercontent.com/OiErU/weather-dashboard/main/posters/cantinho_poster.jpg" />
  </programme>
  <programme start="20260413180000 +0000" stop="20260414000000 +0000" channel="cantinho-meo">
    <title lang="en">🌊 2.9m @ 14s ONSHORE</title>
    <desc lang="en">With that onshore wind and nearly 3-meter swell, today's Cantinho session sounds like a good way to get sandblasted.

🌊 Swell: 2.9m @ 14s
💨 Wind: 16.0km/h W (ONSHORE)
💨 Gusts: 27.0km/h
🌊 Wind waves: 0.4m</desc>
    <icon src="https://raw.githubusercontent.com/OiErU/weather-dashboard/main/posters/cantinho_poster.jpg" />
  </programme>
  <programme start="20260413180000 +0000" stop="20260414000000 +0000" channel="baleal-surfline">
    <title lang="en">🌊 2.9m @ 14s CROSS</title>
    <desc lang="en">With nearly 3m of swell and that wind, today will be a closeout rodeo, best viewed from the cafe.

🌊 Swell: 2.9m @ 14s
💨 Wind: 16.0km/h W (CROSS)
💨 Gusts: 27.0km/h
🌊 Wind waves: 0.4m</desc>
    <icon src="https://raw.githubusercontent.com/OiErU/weather-dashboard/main/posters/baleal_poster.jpg" />
  </programme>
  <programme start="20260413180000 +0000" stop="20260414000000 +0000" channel="lagide-surfline">
    <title lang="en">🌊 2.9m @ 14s CROSS</title>
    <desc lang="en">With a 2.9m swell and that wind, today's session will mostly involve battling chop and regretting decisions.

🌊 Swell: 2.9m @ 14s
💨 Wind: 16.0km/h W (CROSS)
💨 Gusts: 27.0km/h
🌊 Wind waves: 0.4m</desc>
    <icon src="https://raw.githubusercontent.com/OiErU/weather-dashboard/main/posters/lagide_poster.jpg" />
  </programme>
  <programme start="20260413180000 +0000" stop="20260414000000 +0000" channel="lagide-meo">
    <title lang="en">🌊 2.9m @ 14s CROSS</title>
    <desc lang="en">With a 2.9m swell and that wind, today's session will mostly involve battling chop and regretting decisions.

🌊 Swell: 2.9m @ 14s
💨 Wind: 16.0km/h W (CROSS)
💨 Gusts: 27.0km/h
🌊 Wind waves: 0.4m</desc>
    <icon src="https://raw.githubusercontent.com/OiErU/weather-dashboard/main/posters/lagide_poster.jpg" />
  </programme>
  <programme start="20260414000000 +0000" stop="20260414060000 +0000" channel="ericeira-surfline">
    <title lang="en">🌊 2.2m @ 14s ONSHORE</title>
    <desc lang="en">With that onshore wind and 2.2m swell, today will likely be a masterclass in survival, not style.

🌊 Swell: 2.2m @ 14s
💨 Wind: 10.0km/h WNW (ONSHORE)
💨 Gusts: 27.0km/h
🌊 Wind waves: 0.2m</desc>
    <icon src="https://raw.githubusercontent.com/OiErU/weather-dashboard/main/posters/ericeira_poster.jpg" />
  </programme>
  <programme start="20260414000000 +0000" stop="20260414060000 +0000" channel="ericeira-meo">
    <title lang="en">🌊 2.2m @ 14s ONSHORE</title>
    <desc lang="en">With that onshore wind and 2.2m swell, today will likely be a masterclass in survival, not style.

🌊 Swell: 2.2m @ 14s
💨 Wind: 10.0km/h WNW (ONSHORE)
💨 Gusts: 27.0km/h
🌊 Wind waves: 0.2m</desc>
    <icon src="https://raw.githubusercontent.com/OiErU/weather-dashboard/main/posters/ericeira_poster.jpg" />
  </programme>
  <programme start="20260414000000 +0000" stop="20260414060000 +0000" channel="supertubos-surfline">
    <title lang="en">🌊 2.1m @ 14s CROSS</title>
    <desc lang="en">With that wind fighting the 2.1m swell, today's Supertubos will be a closeout rodeo.

🌊 Swell: 2.1m @ 14s
💨 Wind: 10.0km/h WNW (CROSS)
💨 Gusts: 23.0km/h
🌊 Wind waves: 0.2m</desc>
    <icon src="https://raw.githubusercontent.com/OiErU/weather-dashboard/main/posters/supertubos_poster.jpg" />
  </programme>
  <programme start="20260414000000 +0000" stop="20260414060000 +0000" channel="supertubos-meo">
    <title lang="en">🌊 2.1m @ 14s CROSS</title>
    <desc lang="en">With that wind fighting the 2.1m swell, today's Supertubos will be a closeout rodeo.

🌊 Swell: 2.1m @ 14s
💨 Wind: 10.0km/h WNW (CROSS)
💨 Gusts: 23.0km/h
🌊 Wind waves: 0.2m</desc>
    <icon src="https://raw.githubusercontent.com/OiErU/weather-dashboard/main/posters/supertubos_poster.jpg" />
  </programme>
  <programme start="20260414000000 +0000" stop="20260414060000 +0000" channel="molheleste-surfline">
    <title lang="en">🌊 2.1m @ 14s ONSHORE</title>
    <desc lang="en">With 2.1m of onshore wind slop, today's Molhe Leste is best viewed with a beverage from the pier.

🌊 Swell: 2.1m @ 14s
💨 Wind: 10.0km/h WNW (ONSHORE)
💨 Gusts: 23.0km/h
🌊 Wind waves: 0.2m</desc>
    <icon src="https://raw.githubusercontent.com/OiErU/weather-dashboard/main/posters/molheleste_poster.jpg" />
  </programme>
  <programme start="20260414000000 +0000" stop="20260414060000 +0000" channel="molheleste-meo">
    <title lang="en">🌊 2.1m @ 14s ONSHORE</title>
    <desc lang="en">With 2.1m of onshore wind slop, today's Molhe Leste is best viewed with a beverage from the pier.

🌊 Swell: 2.1m @ 14s
💨 Wind: 10.0km/h WNW (ONSHORE)
💨 Gusts: 23.0km/h
🌊 Wind waves: 0.2m</desc>
    <icon src="https://raw.githubusercontent.com/OiErU/weather-dashboard/main/posters/molheleste_poster.jpg" />
  </programme>
  <programme start="20260414000000 +0000" stop="20260414060000 +0000" channel="baia-meo">
    <title lang="en">🌊 2.1m @ 14s ONSHORE</title>
    <desc lang="en">That 2.1m swell with onshore wind might produce some closeouts; bring your swim fins.

🌊 Swell: 2.1m @ 14s
💨 Wind: 10.0km/h WNW (ONSHORE)
💨 Gusts: 23.0km/h
🌊 Wind waves: 0.2m</desc>
    <icon src="https://raw.githubusercontent.com/OiErU/weather-dashboard/main/posters/baleal_poster.jpg" />
  </programme>
  <programme start="20260414000000 +0000" stop="20260414060000 +0000" channel="cantinho-surfline">
    <title lang="en">🌊 2.1m @ 14s ONSHORE</title>
    <desc lang="en">With that wind and 2.1m swell, Cantinho will likely be a washing machine today; maybe watch the carnage with a bica.

🌊 Swell: 2.1m @ 14s
💨 Wind: 10.0km/h WNW (ONSHORE)
💨 Gusts: 23.0km/h
🌊 Wind waves: 0.2m</desc>
    <icon src="https://raw.githubusercontent.com/OiErU/weather-dashboard/main/posters/cantinho_poster.jpg" />
  </programme>
  <programme start="20260414000000 +0000" stop="20260414060000 +0000" channel="cantinho-meo">
    <title lang="en">🌊 2.1m @ 14s ONSHORE</title>
    <desc lang="en">With that wind and 2.1m swell, Cantinho will likely be a washing machine today; maybe watch the carnage with a bica.

🌊 Swell: 2.1m @ 14s
💨 Wind: 10.0km/h WNW (ONSHORE)
💨 Gusts: 23.0km/h
🌊 Wind waves: 0.2m</desc>
    <icon src="https://raw.githubusercontent.com/OiErU/weather-dashboard/main/posters/cantinho_poster.jpg" />
  </programme>
  <programme start="20260414000000 +0000" stop="20260414060000 +0000" channel="baleal-surfline">
    <title lang="en">🌊 2.1m @ 14s CROSS</title>
    <desc lang="en">With that crosswind, those 2-meter waves will be a battle against chop; good luck out there.

🌊 Swell: 2.1m @ 14s
💨 Wind: 10.0km/h WNW (CROSS)
💨 Gusts: 23.0km/h
🌊 Wind waves: 0.2m</desc>
    <icon src="https://raw.githubusercontent.com/OiErU/weather-dashboard/main/posters/baleal_poster.jpg" />
  </programme>
  <programme start="20260414000000 +0000" stop="20260414060000 +0000" channel="lagide-surfline">
    <title lang="en">🌊 2.1m @ 14s CROSS</title>
    <desc lang="en">2.1m and onshore; likely a good day to watch other people struggle.

🌊 Swell: 2.1m @ 14s
💨 Wind: 10.0km/h WNW (CROSS)
💨 Gusts: 23.0km/h
🌊 Wind waves: 0.2m</desc>
    <icon src="https://raw.githubusercontent.com/OiErU/weather-dashboard/main/posters/lagide_poster.jpg" />
  </programme>
  <programme start="20260414000000 +0000" stop="20260414060000 +0000" channel="lagide-meo">
    <title lang="en">🌊 2.1m @ 14s CROSS</title>
    <desc lang="en">2.1m and onshore; likely a good day to watch other people struggle.

🌊 Swell: 2.1m @ 14s
💨 Wind: 10.0km/h WNW (CROSS)
💨 Gusts: 23.0km/h
🌊 Wind waves: 0.2m</desc>
    <icon src="https://raw.githubusercontent.com/OiErU/weather-dashboard/main/posters/lagide_poster.jpg" />
  </programme>
  <programme start="20260414060000 +0000" stop="20260414120000 +0000" channel="ericeira-surfline">
    <title lang="en">🌊 2.5m @ 12s CROSS</title>
    <desc lang="en">The 2.5m swell might offer a few rideable sections before the wind ruins your afternoon.

🌊 Swell: 2.5m @ 12s
💨 Wind: 3.0km/h NW (CROSS)
💨 Gusts: 12.0km/h
🌊 Wind waves: 0.2m</desc>
    <icon src="https://raw.githubusercontent.com/OiErU/weather-dashboard/main/posters/ericeira_poster.jpg" />
  </programme>
  <programme start="20260414060000 +0000" stop="20260414120000 +0000" channel="ericeira-meo">
    <title lang="en">🌊 2.5m @ 12s CROSS</title>
    <desc lang="en">The 2.5m swell might offer a few rideable sections before the wind ruins your afternoon.

🌊 Swell: 2.5m @ 12s
💨 Wind: 3.0km/h NW (CROSS)
💨 Gusts: 12.0km/h
🌊 Wind waves: 0.2m</desc>
    <icon src="https://raw.githubusercontent.com/OiErU/weather-dashboard/main/posters/ericeira_poster.jpg" />
  </programme>
  <programme start="20260414060000 +0000" stop="20260414120000 +0000" channel="supertubos-surfline">
    <title lang="en">🌊 2.3m @ 12s CROSS</title>
    <desc lang="en">2.3 metres and a cross-wind; Supertubos will be separating the wheat from the chaff today.

🌊 Swell: 2.3m @ 12s
💨 Wind: 5.0km/h WNW (CROSS)
💨 Gusts: 9.0km/h
🌊 Wind waves: 0.1m</desc>
    <icon src="https://raw.githubusercontent.com/OiErU/weather-dashboard/main/posters/supertubos_poster.jpg" />
  </programme>
  <programme start="20260414060000 +0000" stop="20260414120000 +0000" channel="supertubos-meo">
    <title lang="en">🌊 2.3m @ 12s CROSS</title>
    <desc lang="en">2.3 metres and a cross-wind; Supertubos will be separating the wheat from the chaff today.

🌊 Swell: 2.3m @ 12s
💨 Wind: 5.0km/h WNW (CROSS)
💨 Gusts: 9.0km/h
🌊 Wind waves: 0.1m</desc>
    <icon src="https://raw.githubusercontent.com/OiErU/weather-dashboard/main/posters/supertubos_poster.jpg" />
  </programme>
  <programme start="20260414060000 +0000" stop="20260414120000 +0000" channel="molheleste-surfline">
    <title lang="en">🌊 2.3m @ 12s ONSHORE</title>
    <desc lang="en">Those 2.3m waves are probably closing out on the inside, best to watch someone else break their board.

🌊 Swell: 2.3m @ 12s
💨 Wind: 5.0km/h WNW (ONSHORE)
💨 Gusts: 9.0km/h
🌊 Wind waves: 0.1m</desc>
    <icon src="https://raw.githubusercontent.com/OiErU/weather-dashboard/main/posters/molheleste_poster.jpg" />
  </programme>
  <programme start="20260414060000 +0000" stop="20260414120000 +0000" channel="molheleste-meo">
    <title lang="en">🌊 2.3m @ 12s ONSHORE</title>
    <desc lang="en">Those 2.3m waves are probably closing out on the inside, best to watch someone else break their board.

🌊 Swell: 2.3m @ 12s
💨 Wind: 5.0km/h WNW (ONSHORE)
💨 Gusts: 9.0km/h
🌊 Wind waves: 0.1m</desc>
    <icon src="https://raw.githubusercontent.com/OiErU/weather-dashboard/main/posters/molheleste_poster.jpg" />
  </programme>
  <programme start="20260414060000 +0000" stop="20260414120000 +0000" channel="baia-meo">
    <title lang="en">🌊 2.3m @ 12s ONSHORE</title>
    <desc lang="en">With 2.3 meters and onshore wind, today's Meio da Baia session will likely be an excellent workout in frustration management.

🌊 Swell: 2.3m @ 12s
💨 Wind: 5.0km/h WNW (ONSHORE)
💨 Gusts: 9.0km/h
🌊 Wind waves: 0.1m</desc>
    <icon src="https://raw.githubusercontent.com/OiErU/weather-dashboard/main/posters/baleal_poster.jpg" />
  </programme>
  <programme start="20260414060000 +0000" stop="20260414120000 +0000" channel="cantinho-surfline">
    <title lang="en">🌊 2.3m @ 12s ONSHORE</title>
    <desc lang="en">With that onshore breeze wrestling a 2.3m swell, Cantinho da Baia will likely be a closeout fiesta today.

🌊 Swell: 2.3m @ 12s
💨 Wind: 5.0km/h WNW (ONSHORE)
💨 Gusts: 9.0km/h
🌊 Wind waves: 0.1m</desc>
    <icon src="https://raw.githubusercontent.com/OiErU/weather-dashboard/main/posters/cantinho_poster.jpg" />
  </programme>
  <programme start="20260414060000 +0000" stop="20260414120000 +0000" channel="cantinho-meo">
    <title lang="en">🌊 2.3m @ 12s ONSHORE</title>
    <desc lang="en">With that onshore breeze wrestling a 2.3m swell, Cantinho da Baia will likely be a closeout fiesta today.

🌊 Swell: 2.3m @ 12s
💨 Wind: 5.0km/h WNW (ONSHORE)
💨 Gusts: 9.0km/h
🌊 Wind waves: 0.1m</desc>
    <icon src="https://raw.githubusercontent.com/OiErU/weather-dashboard/main/posters/cantinho_poster.jpg" />
  </programme>
  <programme start="20260414060000 +0000" stop="20260414120000 +0000" channel="baleal-surfline">
    <title lang="en">🌊 2.3m @ 12s CROSS</title>
    <desc lang="en">With that wind and 2.3m, today's session will likely be a masterclass in damage control.

🌊 Swell: 2.3m @ 12s
💨 Wind: 5.0km/h WNW (CROSS)
💨 Gusts: 9.0km/h
🌊 Wind waves: 0.1m</desc>
    <icon src="https://raw.githubusercontent.com/OiErU/weather-dashboard/main/posters/baleal_poster.jpg" />
  </programme>
  <programme start="20260414060000 +0000" stop="20260414120000 +0000" channel="lagide-surfline">
    <title lang="en">🌊 2.3m @ 12s CROSS</title>
    <desc lang="en">With 2.3 meters and that wind, Lagide might offer some brief excitement before closing out spectacularly.

🌊 Swell: 2.3m @ 12s
💨 Wind: 5.0km/h WNW (CROSS)
💨 Gusts: 9.0km/h
🌊 Wind waves: 0.1m</desc>
    <icon src="https://raw.githubusercontent.com/OiErU/weather-dashboard/main/posters/lagide_poster.jpg" />
  </programme>
  <programme start="20260414060000 +0000" stop="20260414120000 +0000" channel="lagide-meo">
    <title lang="en">🌊 2.3m @ 12s CROSS</title>
    <desc lang="en">With 2.3 meters and that wind, Lagide might offer some brief excitement before closing out spectacularly.

🌊 Swell: 2.3m @ 12s
💨 Wind: 5.0km/h WNW (CROSS)
💨 Gusts: 9.0km/h
🌊 Wind waves: 0.1m</desc>
    <icon src="https://raw.githubusercontent.com/OiErU/weather-dashboard/main/posters/lagide_poster.jpg" />
  </programme>
  <programme start="20260414120000 +0000" stop="20260414180000 +0000" channel="ericeira-surfline">
    <title lang="en">🌊 2.2m @ 12s CROSS</title>
    <desc lang="en">With a 2.2m swell and that crosswind, you'll be wrestling mushburgers out there today.

🌊 Swell: 2.2m @ 12s
💨 Wind: 10.0km/h NW (CROSS)
💨 Gusts: 24.0km/h
🌊 Wind waves: 0.1m</desc>
    <icon src="https://raw.githubusercontent.com/OiErU/weather-dashboard/main/posters/ericeira_poster.jpg" />
  </programme>
  <programme start="20260414120000 +0000" stop="20260414180000 +0000" channel="ericeira-meo">
    <title lang="en">🌊 2.2m @ 12s CROSS</title>
    <desc lang="en">With a 2.2m swell and that crosswind, you'll be wrestling mushburgers out there today.

🌊 Swell: 2.2m @ 12s
💨 Wind: 10.0km/h NW (CROSS)
💨 Gusts: 24.0km/h
🌊 Wind waves: 0.1m</desc>
    <icon src="https://raw.githubusercontent.com/OiErU/weather-dashboard/main/posters/ericeira_poster.jpg" />
  </programme>
  <programme start="20260414120000 +0000" stop="20260414180000 +0000" channel="supertubos-surfline">
    <title lang="en">🌊 1.9m @ 12s CROSS</title>
    <desc lang="en">The 1.9m swell and crosswind suggests a workout more than a wave today.

🌊 Swell: 1.9m @ 12s
💨 Wind: 9.0km/h NW (CROSS)
💨 Gusts: 17.0km/h
🌊 Wind waves: 0.1m</desc>
    <icon src="https://raw.githubusercontent.com/OiErU/weather-dashboard/main/posters/supertubos_poster.jpg" />
  </programme>
  <programme start="20260414120000 +0000" stop="20260414180000 +0000" channel="supertubos-meo">
    <title lang="en">🌊 1.9m @ 12s CROSS</title>
    <desc lang="en">The 1.9m swell and crosswind suggests a workout more than a wave today.

🌊 Swell: 1.9m @ 12s
💨 Wind: 9.0km/h NW (CROSS)
💨 Gusts: 17.0km/h
🌊 Wind waves: 0.1m</desc>
    <icon src="https://raw.githubusercontent.com/OiErU/weather-dashboard/main/posters/supertubos_poster.jpg" />
  </programme>
  <programme start="20260414120000 +0000" stop="20260414180000 +0000" channel="molheleste-surfline">
    <title lang="en">🌊 1.9m @ 12s CROSS</title>
    <desc lang="en">With that wind against a near 2-meter swell, today's Molhe Leste session is best observed from the cafe.

🌊 Swell: 1.9m @ 12s
💨 Wind: 9.0km/h NW (CROSS)
💨 Gusts: 17.0km/h
🌊 Wind waves: 0.1m</desc>
    <icon src="https://raw.githubusercontent.com/OiErU/weather-dashboard/main/posters/molheleste_poster.jpg" />
  </programme>
  <programme start="20260414120000 +0000" stop="20260414180000 +0000" channel="molheleste-meo">
    <title lang="en">🌊 1.9m @ 12s CROSS</title>
    <desc lang="en">With that wind against a near 2-meter swell, today's Molhe Leste session is best observed from the cafe.

🌊 Swell: 1.9m @ 12s
💨 Wind: 9.0km/h NW (CROSS)
💨 Gusts: 17.0km/h
🌊 Wind waves: 0.1m</desc>
    <icon src="https://raw.githubusercontent.com/OiErU/weather-dashboard/main/posters/molheleste_poster.jpg" />
  </programme>
  <programme start="20260414120000 +0000" stop="20260414180000 +0000" channel="baia-meo">
    <title lang="en">🌊 1.9m @ 12s ONSHORE</title>
    <desc lang="en">With 1.9m and that onshore wind, today's session will likely be a closeout fiesta followed by sand in every orifice.

🌊 Swell: 1.9m @ 12s
💨 Wind: 9.0km/h NW (ONSHORE)
💨 Gusts: 17.0km/h
🌊 Wind waves: 0.1m</desc>
    <icon src="https://raw.githubusercontent.com/OiErU/weather-dashboard/main/posters/baleal_poster.jpg" />
  </programme>
  <programme start="20260414120000 +0000" stop="20260414180000 +0000" channel="cantinho-surfline">
    <title lang="en">🌊 1.9m @ 12s ONSHORE</title>
    <desc lang="en">1.  9m and onshore? Looks like Cantinho's serving up closeouts today, enjoy the whitewash.

🌊 Swell: 1.9m @ 12s
💨 Wind: 9.0km/h NW (ONSHORE)
💨 Gusts: 17.0km/h
🌊 Wind waves: 0.1m</desc>
    <icon src="https://raw.githubusercontent.com/OiErU/weather-dashboard/main/posters/cantinho_poster.jpg" />
  </programme>
  <programme start="20260414120000 +0000" stop="20260414180000 +0000" channel="cantinho-meo">
    <title lang="en">🌊 1.9m @ 12s ONSHORE</title>
    <desc lang="en">1.  9m and onshore? Looks like Cantinho's serving up closeouts today, enjoy the whitewash.

🌊 Swell: 1.9m @ 12s
💨 Wind: 9.0km/h NW (ONSHORE)
💨 Gusts: 17.0km/h
🌊 Wind waves: 0.1m</desc>
    <icon src="https://raw.githubusercontent.com/OiErU/weather-dashboard/main/posters/cantinho_poster.jpg" />
  </programme>
  <programme start="20260414120000 +0000" stop="20260414180000 +0000" channel="baleal-surfline">
    <title lang="en">🌊 1.9m @ 12s ONSHORE</title>
    <desc lang="en">At 1.9m and with that wind, today's session is probably best observed from a bar.

🌊 Swell: 1.9m @ 12s
💨 Wind: 9.0km/h NW (ONSHORE)
💨 Gusts: 17.0km/h
🌊 Wind waves: 0.1m</desc>
    <icon src="https://raw.githubusercontent.com/OiErU/weather-dashboard/main/posters/baleal_poster.jpg" />
  </programme>
  <programme start="20260414120000 +0000" stop="20260414180000 +0000" channel="lagide-surfline">
    <title lang="en">🌊 1.9m @ 12s ONSHORE</title>
    <desc lang="en">With 1.9m of onshore slop, Lagide's likely offering closeouts and a hefty dose of sandblasting today.

🌊 Swell: 1.9m @ 12s
💨 Wind: 9.0km/h NW (ONSHORE)
💨 Gusts: 17.0km/h
🌊 Wind waves: 0.1m</desc>
    <icon src="https://raw.githubusercontent.com/OiErU/weather-dashboard/main/posters/lagide_poster.jpg" />
  </programme>
  <programme start="20260414120000 +0000" stop="20260414180000 +0000" channel="lagide-meo">
    <title lang="en">🌊 1.9m @ 12s ONSHORE</title>
    <desc lang="en">With 1.9m of onshore slop, Lagide's likely offering closeouts and a hefty dose of sandblasting today.

🌊 Swell: 1.9m @ 12s
💨 Wind: 9.0km/h NW (ONSHORE)
💨 Gusts: 17.0km/h
🌊 Wind waves: 0.1m</desc>
    <icon src="https://raw.githubusercontent.com/OiErU/weather-dashboard/main/posters/lagide_poster.jpg" />
  </programme>
  <programme start="20260414180000 +0000" stop="20260415000000 +0000" channel="ericeira-surfline">
    <title lang="en">🌊 2.0m @ 12s ONSHORE</title>
    <desc lang="en">That onshore wind will be turning those 2.0m waves into something resembling a washing machine today.

🌊 Swell: 2.0m @ 12s
💨 Wind: 12.0km/h NW (ONSHORE)
💨 Gusts: 29.0km/h
🌊 Wind waves: 0.2m</desc>
    <icon src="https://raw.githubusercontent.com/OiErU/weather-dashboard/main/posters/ericeira_poster.jpg" />
  </programme>
  <programme start="20260414180000 +0000" stop="20260415000000 +0000" channel="ericeira-meo">
    <title lang="en">🌊 2.0m @ 12s ONSHORE</title>
    <desc lang="en">That onshore wind will be turning those 2.0m waves into something resembling a washing machine today.

🌊 Swell: 2.0m @ 12s
💨 Wind: 12.0km/h NW (ONSHORE)
💨 Gusts: 29.0km/h
🌊 Wind waves: 0.2m</desc>
    <icon src="https://raw.githubusercontent.com/OiErU/weather-dashboard/main/posters/ericeira_poster.jpg" />
  </programme>
  <programme start="20260414180000 +0000" stop="20260415000000 +0000" channel="supertubos-surfline">
    <title lang="en">🌊 2.0m @ 12s CROSS</title>
    <desc lang="en">Two meters with that wind? Probably more suited to watching someone else break their board.

🌊 Swell: 2.0m @ 12s
💨 Wind: 12.0km/h NW (CROSS)
💨 Gusts: 22.0km/h
🌊 Wind waves: 0.1m</desc>
    <icon src="https://raw.githubusercontent.com/OiErU/weather-dashboard/main/posters/supertubos_poster.jpg" />
  </programme>
  <programme start="20260414180000 +0000" stop="20260415000000 +0000" channel="supertubos-meo">
    <title lang="en">🌊 2.0m @ 12s CROSS</title>
    <desc lang="en">Two meters with that wind? Probably more suited to watching someone else break their board.

🌊 Swell: 2.0m @ 12s
💨 Wind: 12.0km/h NW (CROSS)
💨 Gusts: 22.0km/h
🌊 Wind waves: 0.1m</desc>
    <icon src="https://raw.githubusercontent.com/OiErU/weather-dashboard/main/posters/supertubos_poster.jpg" />
  </programme>
  <programme start="20260414180000 +0000" stop="20260415000000 +0000" channel="molheleste-surfline">
    <title lang="en">🌊 2.0m @ 12s ONSHORE</title>
    <desc lang="en">With 2.0m and onshore wind, today's Molhe Leste session will likely involve more paddling than riding.

🌊 Swell: 2.0m @ 12s
💨 Wind: 12.0km/h NW (ONSHORE)
💨 Gusts: 22.0km/h
🌊 Wind waves: 0.1m</desc>
    <icon src="https://raw.githubusercontent.com/OiErU/weather-dashboard/main/posters/molheleste_poster.jpg" />
  </programme>
  <programme start="20260414180000 +0000" stop="20260415000000 +0000" channel="molheleste-meo">
    <title lang="en">🌊 2.0m @ 12s ONSHORE</title>
    <desc lang="en">With 2.0m and onshore wind, today's Molhe Leste session will likely involve more paddling than riding.

🌊 Swell: 2.0m @ 12s
💨 Wind: 12.0km/h NW (ONSHORE)
💨 Gusts: 22.0km/h
🌊 Wind waves: 0.1m</desc>
    <icon src="https://raw.githubusercontent.com/OiErU/weather-dashboard/main/posters/molheleste_poster.jpg" />
  </programme>
  <programme start="20260414180000 +0000" stop="20260415000000 +0000" channel="baia-meo">
    <title lang="en">🌊 2.0m @ 12s ONSHORE</title>
    <desc lang="en">Two meters and onshore wind; I've seen worse days to watch the shorebirds.

🌊 Swell: 2.0m @ 12s
💨 Wind: 12.0km/h NW (ONSHORE)
💨 Gusts: 22.0km/h
🌊 Wind waves: 0.1m</desc>
    <icon src="https://raw.githubusercontent.com/OiErU/weather-dashboard/main/posters/baleal_poster.jpg" />
  </programme>
  <programme start="20260414180000 +0000" stop="20260415000000 +0000" channel="cantinho-surfline">
    <title lang="en">🌊 2.0m @ 12s ONSHORE</title>
    <desc lang="en">Two meters with onshore wind? Today, the only ride will be on my couch.

🌊 Swell: 2.0m @ 12s
💨 Wind: 12.0km/h NW (ONSHORE)
💨 Gusts: 22.0km/h
🌊 Wind waves: 0.1m</desc>
    <icon src="https://raw.githubusercontent.com/OiErU/weather-dashboard/main/posters/cantinho_poster.jpg" />
  </programme>
  <programme start="20260414180000 +0000" stop="20260415000000 +0000" channel="cantinho-meo">
    <title lang="en">🌊 2.0m @ 12s ONSHORE</title>
    <desc lang="en">Two meters with onshore wind? Today, the only ride will be on my couch.

🌊 Swell: 2.0m @ 12s
💨 Wind: 12.0km/h NW (ONSHORE)
💨 Gusts: 22.0km/h
🌊 Wind waves: 0.1m</desc>
    <icon src="https://raw.githubusercontent.com/OiErU/weather-dashboard/main/posters/cantinho_poster.jpg" />
  </programme>
  <programme start="20260414180000 +0000" stop="20260415000000 +0000" channel="baleal-surfline">
    <title lang="en">🌊 2.0m @ 12s ONSHORE</title>
    <desc lang="en">Two meters and onshore at Baleal Norte? Best to watch the seagulls fight over scraps today.

🌊 Swell: 2.0m @ 12s
💨 Wind: 12.0km/h NW (ONSHORE)
💨 Gusts: 22.0km/h
🌊 Wind waves: 0.1m</desc>
    <icon src="https://raw.githubusercontent.com/OiErU/weather-dashboard/main/posters/baleal_poster.jpg" />
  </programme>
  <programme start="20260414180000 +0000" stop="20260415000000 +0000" channel="lagide-surfline">
    <title lang="en">🌊 2.0m @ 12s ONSHORE</title>
    <desc lang="en">Those 2.0m waves with onshore wind will offer more frustration than thrills today.

🌊 Swell: 2.0m @ 12s
💨 Wind: 12.0km/h NW (ONSHORE)
💨 Gusts: 22.0km/h
🌊 Wind waves: 0.1m</desc>
    <icon src="https://raw.githubusercontent.com/OiErU/weather-dashboard/main/posters/lagide_poster.jpg" />
  </programme>
  <programme start="20260414180000 +0000" stop="20260415000000 +0000" channel="lagide-meo">
    <title lang="en">🌊 2.0m @ 12s ONSHORE</title>
    <desc lang="en">Those 2.0m waves with onshore wind will offer more frustration than thrills today.

🌊 Swell: 2.0m @ 12s
💨 Wind: 12.0km/h NW (ONSHORE)
💨 Gusts: 22.0km/h
🌊 Wind waves: 0.1m</desc>
    <icon src="https://raw.githubusercontent.com/OiErU/weather-dashboard/main/posters/lagide_poster.jpg" />
  </programme>
</tv>