<?xml version='1.0' encoding='utf-8'?>
<tv generator-info-name="Surf EPG (Open-Meteo)" generator-info-url="https://raw.githubusercontent.com/OiErU/weather-dashboard/main">
  <channel id="ericeira-surfline">
    <display-name>Surfline Ericeira</display-name>
    <icon src="https://raw.githubusercontent.com/OiErU/weather-dashboard/main/logos/ericeira.png?v=2" />
  </channel>
  <channel id="ericeira-meo">
    <display-name>MEO Ericeira</display-name>
    <icon src="https://raw.githubusercontent.com/OiErU/weather-dashboard/main/logos/ericeira.png?v=2" />
  </channel>
  <channel id="supertubos-surfline">
    <display-name>Surfline Supertubos</display-name>
    <icon src="https://raw.githubusercontent.com/OiErU/weather-dashboard/main/logos/supertubos.png?v=2" />
  </channel>
  <channel id="supertubos-meo">
    <display-name>MEO Supertubos</display-name>
    <icon src="https://raw.githubusercontent.com/OiErU/weather-dashboard/main/logos/supertubos.png?v=2" />
  </channel>
  <channel id="molheleste-surfline">
    <display-name>Surfline Molhe Leste</display-name>
    <icon src="https://raw.githubusercontent.com/OiErU/weather-dashboard/main/logos/molheleste.png?v=2" />
  </channel>
  <channel id="molheleste-meo">
    <display-name>MEO Molhe Leste</display-name>
    <icon src="https://raw.githubusercontent.com/OiErU/weather-dashboard/main/logos/molheleste.png?v=2" />
  </channel>
  <channel id="baia-meo">
    <display-name>MEO Baia</display-name>
    <icon src="https://raw.githubusercontent.com/OiErU/weather-dashboard/main/logos/baleal.png?v=2" />
  </channel>
  <channel id="cantinho-surfline">
    <display-name>Surfline Cantinho</display-name>
    <icon src="https://raw.githubusercontent.com/OiErU/weather-dashboard/main/logos/cantinho.png?v=2" />
  </channel>
  <channel id="cantinho-meo">
    <display-name>MEO Cantinho</display-name>
    <icon src="https://raw.githubusercontent.com/OiErU/weather-dashboard/main/logos/cantinho.png?v=2" />
  </channel>
  <channel id="baleal-surfline">
    <display-name>Surfline Baleal</display-name>
    <icon src="https://raw.githubusercontent.com/OiErU/weather-dashboard/main/logos/baleal.png?v=2" />
  </channel>
  <channel id="lagide-surfline">
    <display-name>Surfline Lagide</display-name>
    <icon src="https://raw.githubusercontent.com/OiErU/weather-dashboard/main/logos/lagide.png?v=2" />
  </channel>
  <channel id="lagide-meo">
    <display-name>MEO Lagide</display-name>
    <icon src="https://raw.githubusercontent.com/OiErU/weather-dashboard/main/logos/lagide.png?v=2" />
  </channel>
  <programme start="20260522000000 +0000" stop="20260522060000 +0000" channel="ericeira-surfline">
    <title lang="en">⭐⭐ 1.4m @ 11s OFFSHORE</title>
    <desc lang="en">Offshore wind and a 1.4m swell; could be worse, probably will be later.

🌊 Swell: 1.4m @ 11s
💨 Wind: 6.0km/h ESE (OFFSHORE)
💨 Gusts: 14.0km/h
🌊 Wind waves: 0.0m

📋 Clean conditions with offshore wind</desc>
    <icon src="https://raw.githubusercontent.com/OiErU/weather-dashboard/main/posters/ericeira_poster.jpg" />
  </programme>
  <programme start="20260522000000 +0000" stop="20260522060000 +0000" channel="ericeira-meo">
    <title lang="en">⭐⭐ 1.4m @ 11s OFFSHORE</title>
    <desc lang="en">Offshore wind and a 1.4m swell; could be worse, probably will be later.

🌊 Swell: 1.4m @ 11s
💨 Wind: 6.0km/h ESE (OFFSHORE)
💨 Gusts: 14.0km/h
🌊 Wind waves: 0.0m

📋 Clean conditions with offshore wind</desc>
    <icon src="https://raw.githubusercontent.com/OiErU/weather-dashboard/main/posters/ericeira_poster.jpg" />
  </programme>
  <programme start="20260522000000 +0000" stop="20260522060000 +0000" channel="supertubos-surfline">
    <title lang="en">🌊 1.3m @ 11s CROSS</title>
    <desc lang="en">The 1.3m swell might offer a ride or two before the wind turns it to chop suey.

🌊 Swell: 1.3m @ 11s
💨 Wind: 4.0km/h ESE (CROSS)
💨 Gusts: 6.0km/h
🌊 Wind waves: 0.0m</desc>
    <icon src="https://raw.githubusercontent.com/OiErU/weather-dashboard/main/posters/supertubos_poster.jpg" />
  </programme>
  <programme start="20260522000000 +0000" stop="20260522060000 +0000" channel="supertubos-meo">
    <title lang="en">🌊 1.3m @ 11s CROSS</title>
    <desc lang="en">The 1.3m swell might offer a ride or two before the wind turns it to chop suey.

🌊 Swell: 1.3m @ 11s
💨 Wind: 4.0km/h ESE (CROSS)
💨 Gusts: 6.0km/h
🌊 Wind waves: 0.0m</desc>
    <icon src="https://raw.githubusercontent.com/OiErU/weather-dashboard/main/posters/supertubos_poster.jpg" />
  </programme>
  <programme start="20260522000000 +0000" stop="20260522060000 +0000" channel="molheleste-surfline">
    <title lang="en">⭐⭐ 1.3m @ 11s OFFSHORE</title>
    <desc lang="en">A clean 1.3m swell with offshore wind; might actually be worth getting wet today, surprisingly.

🌊 Swell: 1.3m @ 11s
💨 Wind: 4.0km/h ESE (OFFSHORE)
💨 Gusts: 6.0km/h
🌊 Wind waves: 0.0m

📋 Clean conditions with offshore wind</desc>
    <icon src="https://raw.githubusercontent.com/OiErU/weather-dashboard/main/posters/molheleste_poster.jpg" />
  </programme>
  <programme start="20260522000000 +0000" stop="20260522060000 +0000" channel="molheleste-meo">
    <title lang="en">⭐⭐ 1.3m @ 11s OFFSHORE</title>
    <desc lang="en">A clean 1.3m swell with offshore wind; might actually be worth getting wet today, surprisingly.

🌊 Swell: 1.3m @ 11s
💨 Wind: 4.0km/h ESE (OFFSHORE)
💨 Gusts: 6.0km/h
🌊 Wind waves: 0.0m

📋 Clean conditions with offshore wind</desc>
    <icon src="https://raw.githubusercontent.com/OiErU/weather-dashboard/main/posters/molheleste_poster.jpg" />
  </programme>
  <programme start="20260522000000 +0000" stop="20260522060000 +0000" channel="baia-meo">
    <title lang="en">⭐⭐ 1.3m @ 11s OFFSHORE</title>
    <desc lang="en">1.3 meters with offshore wind? Might get a ride or two before the crowd figures it out.

🌊 Swell: 1.3m @ 11s
💨 Wind: 4.0km/h ESE (OFFSHORE)
💨 Gusts: 6.0km/h
🌊 Wind waves: 0.0m

📋 Clean conditions with offshore wind</desc>
    <icon src="https://raw.githubusercontent.com/OiErU/weather-dashboard/main/posters/baleal_poster.jpg" />
  </programme>
  <programme start="20260522000000 +0000" stop="20260522060000 +0000" channel="cantinho-surfline">
    <title lang="en">⭐⭐ 1.3m @ 11s OFFSHORE</title>
    <desc lang="en">That 1.3m swell with offshore wind might produce a few rideable nuggets, or just a lot of paddling.

🌊 Swell: 1.3m @ 11s
💨 Wind: 4.0km/h ESE (OFFSHORE)
💨 Gusts: 6.0km/h
🌊 Wind waves: 0.0m

📋 Clean conditions with offshore wind</desc>
    <icon src="https://raw.githubusercontent.com/OiErU/weather-dashboard/main/posters/cantinho_poster.jpg" />
  </programme>
  <programme start="20260522000000 +0000" stop="20260522060000 +0000" channel="cantinho-meo">
    <title lang="en">⭐⭐ 1.3m @ 11s OFFSHORE</title>
    <desc lang="en">That 1.3m swell with offshore wind might produce a few rideable nuggets, or just a lot of paddling.

🌊 Swell: 1.3m @ 11s
💨 Wind: 4.0km/h ESE (OFFSHORE)
💨 Gusts: 6.0km/h
🌊 Wind waves: 0.0m

📋 Clean conditions with offshore wind</desc>
    <icon src="https://raw.githubusercontent.com/OiErU/weather-dashboard/main/posters/cantinho_poster.jpg" />
  </programme>
  <programme start="20260522000000 +0000" stop="20260522060000 +0000" channel="baleal-surfline">
    <title lang="en">🌊 1.3m @ 11s CROSS</title>
    <desc lang="en">Might be some rideable 1.3m lumps out there, depending how much the wind messes things up.

🌊 Swell: 1.3m @ 11s
💨 Wind: 4.0km/h ESE (CROSS)
💨 Gusts: 6.0km/h
🌊 Wind waves: 0.0m</desc>
    <icon src="https://raw.githubusercontent.com/OiErU/weather-dashboard/main/posters/baleal_poster.jpg" />
  </programme>
  <programme start="20260522000000 +0000" stop="20260522060000 +0000" channel="lagide-surfline">
    <title lang="en">🌊 1.3m @ 11s CROSS</title>
    <desc lang="en">Lagide might offer a rideable 1.3m wave, assuming the crosswind doesn't completely ruin it.

🌊 Swell: 1.3m @ 11s
💨 Wind: 4.0km/h ESE (CROSS)
💨 Gusts: 6.0km/h
🌊 Wind waves: 0.0m</desc>
    <icon src="https://raw.githubusercontent.com/OiErU/weather-dashboard/main/posters/lagide_poster.jpg" />
  </programme>
  <programme start="20260522000000 +0000" stop="20260522060000 +0000" channel="lagide-meo">
    <title lang="en">🌊 1.3m @ 11s CROSS</title>
    <desc lang="en">Lagide might offer a rideable 1.3m wave, assuming the crosswind doesn't completely ruin it.

🌊 Swell: 1.3m @ 11s
💨 Wind: 4.0km/h ESE (CROSS)
💨 Gusts: 6.0km/h
🌊 Wind waves: 0.0m</desc>
    <icon src="https://raw.githubusercontent.com/OiErU/weather-dashboard/main/posters/lagide_poster.jpg" />
  </programme>
  <programme start="20260522060000 +0000" stop="20260522120000 +0000" channel="ericeira-surfline">
    <title lang="en">🌊 1.5m @ 11s CROSS</title>
    <desc lang="en">The 1.5m swell might offer a ride or two before the crosswind turns it all to soup.

🌊 Swell: 1.5m @ 11s
💨 Wind: 1.0km/h NNE (CROSS)
💨 Gusts: 12.0km/h
🌊 Wind waves: 0.0m</desc>
    <icon src="https://raw.githubusercontent.com/OiErU/weather-dashboard/main/posters/ericeira_poster.jpg" />
  </programme>
  <programme start="20260522060000 +0000" stop="20260522120000 +0000" channel="ericeira-meo">
    <title lang="en">🌊 1.5m @ 11s CROSS</title>
    <desc lang="en">The 1.5m swell might offer a ride or two before the crosswind turns it all to soup.

🌊 Swell: 1.5m @ 11s
💨 Wind: 1.0km/h NNE (CROSS)
💨 Gusts: 12.0km/h
🌊 Wind waves: 0.0m</desc>
    <icon src="https://raw.githubusercontent.com/OiErU/weather-dashboard/main/posters/ericeira_poster.jpg" />
  </programme>
  <programme start="20260522060000 +0000" stop="20260522120000 +0000" channel="supertubos-surfline">
    <title lang="en">🌊 1.4m @ 11s CROSS</title>
    <desc lang="en">Those 1.4m Supertubos might offer a ride or two, assuming the wind doesn't turn them inside out.

🌊 Swell: 1.4m @ 11s
💨 Wind: 4.0km/h WNW (CROSS)
💨 Gusts: 6.0km/h
🌊 Wind waves: 0.0m</desc>
    <icon src="https://raw.githubusercontent.com/OiErU/weather-dashboard/main/posters/supertubos_poster.jpg" />
  </programme>
  <programme start="20260522060000 +0000" stop="20260522120000 +0000" channel="supertubos-meo">
    <title lang="en">🌊 1.4m @ 11s CROSS</title>
    <desc lang="en">Those 1.4m Supertubos might offer a ride or two, assuming the wind doesn't turn them inside out.

🌊 Swell: 1.4m @ 11s
💨 Wind: 4.0km/h WNW (CROSS)
💨 Gusts: 6.0km/h
🌊 Wind waves: 0.0m</desc>
    <icon src="https://raw.githubusercontent.com/OiErU/weather-dashboard/main/posters/supertubos_poster.jpg" />
  </programme>
  <programme start="20260522060000 +0000" stop="20260522120000 +0000" channel="molheleste-surfline">
    <title lang="en">🌊 1.4m @ 11s ONSHORE</title>
    <desc lang="en">1.  4m and onshore? Might be good for practicing duck diving, mostly.

🌊 Swell: 1.4m @ 11s
💨 Wind: 4.0km/h WNW (ONSHORE)
💨 Gusts: 6.0km/h
🌊 Wind waves: 0.0m</desc>
    <icon src="https://raw.githubusercontent.com/OiErU/weather-dashboard/main/posters/molheleste_poster.jpg" />
  </programme>
  <programme start="20260522060000 +0000" stop="20260522120000 +0000" channel="molheleste-meo">
    <title lang="en">🌊 1.4m @ 11s ONSHORE</title>
    <desc lang="en">1.  4m and onshore? Might be good for practicing duck diving, mostly.

🌊 Swell: 1.4m @ 11s
💨 Wind: 4.0km/h WNW (ONSHORE)
💨 Gusts: 6.0km/h
🌊 Wind waves: 0.0m</desc>
    <icon src="https://raw.githubusercontent.com/OiErU/weather-dashboard/main/posters/molheleste_poster.jpg" />
  </programme>
  <programme start="20260522060000 +0000" stop="20260522120000 +0000" channel="baia-meo">
    <title lang="en">🌊 1.4m @ 11s ONSHORE</title>
    <desc lang="en">At 1.4m with that onshore breeze, today will be a masterclass in closeout avoidance.

🌊 Swell: 1.4m @ 11s
💨 Wind: 4.0km/h WNW (ONSHORE)
💨 Gusts: 6.0km/h
🌊 Wind waves: 0.0m</desc>
    <icon src="https://raw.githubusercontent.com/OiErU/weather-dashboard/main/posters/baleal_poster.jpg" />
  </programme>
  <programme start="20260522060000 +0000" stop="20260522120000 +0000" channel="cantinho-surfline">
    <title lang="en">🌊 1.4m @ 11s ONSHORE</title>
    <desc lang="en">The 1.4m swell and onshore breeze suggest a choppy struggle punctuated by moments of fleeting glory, or utter humiliation.

🌊 Swell: 1.4m @ 11s
💨 Wind: 4.0km/h WNW (ONSHORE)
💨 Gusts: 6.0km/h
🌊 Wind waves: 0.0m</desc>
    <icon src="https://raw.githubusercontent.com/OiErU/weather-dashboard/main/posters/cantinho_poster.jpg" />
  </programme>
  <programme start="20260522060000 +0000" stop="20260522120000 +0000" channel="cantinho-meo">
    <title lang="en">🌊 1.4m @ 11s ONSHORE</title>
    <desc lang="en">The 1.4m swell and onshore breeze suggest a choppy struggle punctuated by moments of fleeting glory, or utter humiliation.

🌊 Swell: 1.4m @ 11s
💨 Wind: 4.0km/h WNW (ONSHORE)
💨 Gusts: 6.0km/h
🌊 Wind waves: 0.0m</desc>
    <icon src="https://raw.githubusercontent.com/OiErU/weather-dashboard/main/posters/cantinho_poster.jpg" />
  </programme>
  <programme start="20260522060000 +0000" stop="20260522120000 +0000" channel="baleal-surfline">
    <title lang="en">🌊 1.4m @ 11s CROSS</title>
    <desc lang="en">1.4 meters with that wind? It'll be... character-building, let's say.

🌊 Swell: 1.4m @ 11s
💨 Wind: 4.0km/h WNW (CROSS)
💨 Gusts: 6.0km/h
🌊 Wind waves: 0.0m</desc>
    <icon src="https://raw.githubusercontent.com/OiErU/weather-dashboard/main/posters/baleal_poster.jpg" />
  </programme>
  <programme start="20260522060000 +0000" stop="20260522120000 +0000" channel="lagide-surfline">
    <title lang="en">🌊 1.4m @ 11s CROSS</title>
    <desc lang="en">The 1.4m swell and crosswind suggest a choppy session where you might get lucky or just get tumbled.

🌊 Swell: 1.4m @ 11s
💨 Wind: 4.0km/h WNW (CROSS)
💨 Gusts: 6.0km/h
🌊 Wind waves: 0.0m</desc>
    <icon src="https://raw.githubusercontent.com/OiErU/weather-dashboard/main/posters/lagide_poster.jpg" />
  </programme>
  <programme start="20260522060000 +0000" stop="20260522120000 +0000" channel="lagide-meo">
    <title lang="en">🌊 1.4m @ 11s CROSS</title>
    <desc lang="en">The 1.4m swell and crosswind suggest a choppy session where you might get lucky or just get tumbled.

🌊 Swell: 1.4m @ 11s
💨 Wind: 4.0km/h WNW (CROSS)
💨 Gusts: 6.0km/h
🌊 Wind waves: 0.0m</desc>
    <icon src="https://raw.githubusercontent.com/OiErU/weather-dashboard/main/posters/lagide_poster.jpg" />
  </programme>
  <programme start="20260522120000 +0000" stop="20260522180000 +0000" channel="ericeira-surfline">
    <title lang="en">🌊 1.5m @ 11s CROSS</title>
    <desc lang="en">The 1.5m swell might offer a ride or two, assuming the crosswind doesn't turn it to soup.

🌊 Swell: 1.5m @ 11s
💨 Wind: 8.0km/h NNW (CROSS)
💨 Gusts: 18.0km/h
🌊 Wind waves: 0.0m</desc>
    <icon src="https://raw.githubusercontent.com/OiErU/weather-dashboard/main/posters/ericeira_poster.jpg" />
  </programme>
  <programme start="20260522120000 +0000" stop="20260522180000 +0000" channel="ericeira-meo">
    <title lang="en">🌊 1.5m @ 11s CROSS</title>
    <desc lang="en">The 1.5m swell might offer a ride or two, assuming the crosswind doesn't turn it to soup.

🌊 Swell: 1.5m @ 11s
💨 Wind: 8.0km/h NNW (CROSS)
💨 Gusts: 18.0km/h
🌊 Wind waves: 0.0m</desc>
    <icon src="https://raw.githubusercontent.com/OiErU/weather-dashboard/main/posters/ericeira_poster.jpg" />
  </programme>
  <programme start="20260522120000 +0000" stop="20260522180000 +0000" channel="supertubos-surfline">
    <title lang="en">🌊 1.5m @ 11s CROSS</title>
    <desc lang="en">Those 1.5m waves will offer a ride or two, though that wind suggests more chop than thrill.

🌊 Swell: 1.5m @ 11s
💨 Wind: 8.0km/h NNW (CROSS)
💨 Gusts: 16.0km/h
🌊 Wind waves: 0.0m</desc>
    <icon src="https://raw.githubusercontent.com/OiErU/weather-dashboard/main/posters/supertubos_poster.jpg" />
  </programme>
  <programme start="20260522120000 +0000" stop="20260522180000 +0000" channel="supertubos-meo">
    <title lang="en">🌊 1.5m @ 11s CROSS</title>
    <desc lang="en">Those 1.5m waves will offer a ride or two, though that wind suggests more chop than thrill.

🌊 Swell: 1.5m @ 11s
💨 Wind: 8.0km/h NNW (CROSS)
💨 Gusts: 16.0km/h
🌊 Wind waves: 0.0m</desc>
    <icon src="https://raw.githubusercontent.com/OiErU/weather-dashboard/main/posters/supertubos_poster.jpg" />
  </programme>
  <programme start="20260522120000 +0000" stop="20260522180000 +0000" channel="molheleste-surfline">
    <title lang="en">🌊 1.5m @ 11s CROSS</title>
    <desc lang="en">The 1.5m swell might offer a ride or two, provided the wind doesn't turn it into complete garbage.

🌊 Swell: 1.5m @ 11s
💨 Wind: 8.0km/h NNW (CROSS)
💨 Gusts: 16.0km/h
🌊 Wind waves: 0.0m</desc>
    <icon src="https://raw.githubusercontent.com/OiErU/weather-dashboard/main/posters/molheleste_poster.jpg" />
  </programme>
  <programme start="20260522120000 +0000" stop="20260522180000 +0000" channel="molheleste-meo">
    <title lang="en">🌊 1.5m @ 11s CROSS</title>
    <desc lang="en">The 1.5m swell might offer a ride or two, provided the wind doesn't turn it into complete garbage.

🌊 Swell: 1.5m @ 11s
💨 Wind: 8.0km/h NNW (CROSS)
💨 Gusts: 16.0km/h
🌊 Wind waves: 0.0m</desc>
    <icon src="https://raw.githubusercontent.com/OiErU/weather-dashboard/main/posters/molheleste_poster.jpg" />
  </programme>
  <programme start="20260522120000 +0000" stop="20260522180000 +0000" channel="baia-meo">
    <title lang="en">🌊 1.5m @ 11s ONSHORE</title>
    <desc lang="en">With onshore wind and a 1.5m swell, today's session promises a vigorous workout paddling against the slop.

🌊 Swell: 1.5m @ 11s
💨 Wind: 8.0km/h NNW (ONSHORE)
💨 Gusts: 16.0km/h
🌊 Wind waves: 0.0m</desc>
    <icon src="https://raw.githubusercontent.com/OiErU/weather-dashboard/main/posters/baleal_poster.jpg" />
  </programme>
  <programme start="20260522120000 +0000" stop="20260522180000 +0000" channel="cantinho-surfline">
    <title lang="en">🌊 1.5m @ 11s ONSHORE</title>
    <desc lang="en">Those 1.5m waves will be bumpy and short-lived; I've seen worse, but also better.

🌊 Swell: 1.5m @ 11s
💨 Wind: 8.0km/h NNW (ONSHORE)
💨 Gusts: 16.0km/h
🌊 Wind waves: 0.0m</desc>
    <icon src="https://raw.githubusercontent.com/OiErU/weather-dashboard/main/posters/cantinho_poster.jpg" />
  </programme>
  <programme start="20260522120000 +0000" stop="20260522180000 +0000" channel="cantinho-meo">
    <title lang="en">🌊 1.5m @ 11s ONSHORE</title>
    <desc lang="en">Those 1.5m waves will be bumpy and short-lived; I've seen worse, but also better.

🌊 Swell: 1.5m @ 11s
💨 Wind: 8.0km/h NNW (ONSHORE)
💨 Gusts: 16.0km/h
🌊 Wind waves: 0.0m</desc>
    <icon src="https://raw.githubusercontent.com/OiErU/weather-dashboard/main/posters/cantinho_poster.jpg" />
  </programme>
  <programme start="20260522120000 +0000" stop="20260522180000 +0000" channel="baleal-surfline">
    <title lang="en">🌊 1.5m @ 11s ONSHORE</title>
    <desc lang="en">The 1.5m swell is manageable, but the onshore wind suggests a choppy workout rather than a graceful dance.

🌊 Swell: 1.5m @ 11s
💨 Wind: 8.0km/h NNW (ONSHORE)
💨 Gusts: 16.0km/h
🌊 Wind waves: 0.0m</desc>
    <icon src="https://raw.githubusercontent.com/OiErU/weather-dashboard/main/posters/baleal_poster.jpg" />
  </programme>
  <programme start="20260522120000 +0000" stop="20260522180000 +0000" channel="lagide-surfline">
    <title lang="en">🌊 1.5m @ 11s ONSHORE</title>
    <desc lang="en">The wind might ruffle the 1.5m faces, but at least you'll get wet.

🌊 Swell: 1.5m @ 11s
💨 Wind: 8.0km/h NNW (ONSHORE)
💨 Gusts: 16.0km/h
🌊 Wind waves: 0.0m</desc>
    <icon src="https://raw.githubusercontent.com/OiErU/weather-dashboard/main/posters/lagide_poster.jpg" />
  </programme>
  <programme start="20260522120000 +0000" stop="20260522180000 +0000" channel="lagide-meo">
    <title lang="en">🌊 1.5m @ 11s ONSHORE</title>
    <desc lang="en">The wind might ruffle the 1.5m faces, but at least you'll get wet.

🌊 Swell: 1.5m @ 11s
💨 Wind: 8.0km/h NNW (ONSHORE)
💨 Gusts: 16.0km/h
🌊 Wind waves: 0.0m</desc>
    <icon src="https://raw.githubusercontent.com/OiErU/weather-dashboard/main/posters/lagide_poster.jpg" />
  </programme>
  <programme start="20260522180000 +0000" stop="20260523000000 +0000" channel="ericeira-surfline">
    <title lang="en">🌊 1.5m @ 11s CROSS</title>
    <desc lang="en">A metre and a half with that wind? Expect a chop-fest and some exercise.

🌊 Swell: 1.5m @ 11s
💨 Wind: 18.0km/h N (CROSS)
💨 Gusts: 36.0km/h
🌊 Wind waves: 0.3m</desc>
    <icon src="https://raw.githubusercontent.com/OiErU/weather-dashboard/main/posters/ericeira_poster.jpg" />
  </programme>
  <programme start="20260522180000 +0000" stop="20260523000000 +0000" channel="ericeira-meo">
    <title lang="en">🌊 1.5m @ 11s CROSS</title>
    <desc lang="en">A metre and a half with that wind? Expect a chop-fest and some exercise.

🌊 Swell: 1.5m @ 11s
💨 Wind: 18.0km/h N (CROSS)
💨 Gusts: 36.0km/h
🌊 Wind waves: 0.3m</desc>
    <icon src="https://raw.githubusercontent.com/OiErU/weather-dashboard/main/posters/ericeira_poster.jpg" />
  </programme>
  <programme start="20260522180000 +0000" stop="20260523000000 +0000" channel="supertubos-surfline">
    <title lang="en">⭐⭐ 1.4m @ 11s OFFSHORE</title>
    <desc lang="en">The 1.4 meter swell might offer a ride or two before the crowd descends and someone ends up on the beach in Figueira da Foz.

🌊 Swell: 1.4m @ 11s
💨 Wind: 17.0km/h N (OFFSHORE)
💨 Gusts: 29.0km/h
🌊 Wind waves: 0.2m

📋 Clean conditions with offshore wind</desc>
    <icon src="https://raw.githubusercontent.com/OiErU/weather-dashboard/main/posters/supertubos_poster.jpg" />
  </programme>
  <programme start="20260522180000 +0000" stop="20260523000000 +0000" channel="supertubos-meo">
    <title lang="en">⭐⭐ 1.4m @ 11s OFFSHORE</title>
    <desc lang="en">The 1.4 meter swell might offer a ride or two before the crowd descends and someone ends up on the beach in Figueira da Foz.

🌊 Swell: 1.4m @ 11s
💨 Wind: 17.0km/h N (OFFSHORE)
💨 Gusts: 29.0km/h
🌊 Wind waves: 0.2m

📋 Clean conditions with offshore wind</desc>
    <icon src="https://raw.githubusercontent.com/OiErU/weather-dashboard/main/posters/supertubos_poster.jpg" />
  </programme>
  <programme start="20260522180000 +0000" stop="20260523000000 +0000" channel="molheleste-surfline">
    <title lang="en">🌊 1.4m @ 11s CROSS</title>
    <desc lang="en">1.4 meters with a crosswind; I've seen worse, mostly last week.

🌊 Swell: 1.4m @ 11s
💨 Wind: 17.0km/h N (CROSS)
💨 Gusts: 29.0km/h
🌊 Wind waves: 0.2m</desc>
    <icon src="https://raw.githubusercontent.com/OiErU/weather-dashboard/main/posters/molheleste_poster.jpg" />
  </programme>
  <programme start="20260522180000 +0000" stop="20260523000000 +0000" channel="molheleste-meo">
    <title lang="en">🌊 1.4m @ 11s CROSS</title>
    <desc lang="en">1.4 meters with a crosswind; I've seen worse, mostly last week.

🌊 Swell: 1.4m @ 11s
💨 Wind: 17.0km/h N (CROSS)
💨 Gusts: 29.0km/h
🌊 Wind waves: 0.2m</desc>
    <icon src="https://raw.githubusercontent.com/OiErU/weather-dashboard/main/posters/molheleste_poster.jpg" />
  </programme>
  <programme start="20260522180000 +0000" stop="20260523000000 +0000" channel="baia-meo">
    <title lang="en">🌊 1.4m @ 11s CROSS</title>
    <desc lang="en">Those 1.4m waves will probably close out before you get a decent ride; might be good for a swim, though.

🌊 Swell: 1.4m @ 11s
💨 Wind: 17.0km/h N (CROSS)
💨 Gusts: 29.0km/h
🌊 Wind waves: 0.2m</desc>
    <icon src="https://raw.githubusercontent.com/OiErU/weather-dashboard/main/posters/baleal_poster.jpg" />
  </programme>
  <programme start="20260522180000 +0000" stop="20260523000000 +0000" channel="cantinho-surfline">
    <title lang="en">🌊 1.4m @ 11s ONSHORE</title>
    <desc lang="en">With that onshore breeze, the 1.4m swell will be producing something...probably frustration.

🌊 Swell: 1.4m @ 11s
💨 Wind: 17.0km/h N (ONSHORE)
💨 Gusts: 29.0km/h
🌊 Wind waves: 0.2m</desc>
    <icon src="https://raw.githubusercontent.com/OiErU/weather-dashboard/main/posters/cantinho_poster.jpg" />
  </programme>
  <programme start="20260522180000 +0000" stop="20260523000000 +0000" channel="cantinho-meo">
    <title lang="en">🌊 1.4m @ 11s ONSHORE</title>
    <desc lang="en">With that onshore breeze, the 1.4m swell will be producing something...probably frustration.

🌊 Swell: 1.4m @ 11s
💨 Wind: 17.0km/h N (ONSHORE)
💨 Gusts: 29.0km/h
🌊 Wind waves: 0.2m</desc>
    <icon src="https://raw.githubusercontent.com/OiErU/weather-dashboard/main/posters/cantinho_poster.jpg" />
  </programme>
  <programme start="20260522180000 +0000" stop="20260523000000 +0000" channel="baleal-surfline">
    <title lang="en">🌊 1.4m @ 11s ONSHORE</title>
    <desc lang="en">With 1.4m and onshore breeze, today's session will be a character-building exercise at best.

🌊 Swell: 1.4m @ 11s
💨 Wind: 17.0km/h N (ONSHORE)
💨 Gusts: 29.0km/h
🌊 Wind waves: 0.2m</desc>
    <icon src="https://raw.githubusercontent.com/OiErU/weather-dashboard/main/posters/baleal_poster.jpg" />
  </programme>
  <programme start="20260522180000 +0000" stop="20260523000000 +0000" channel="lagide-surfline">
    <title lang="en">🌊 1.4m @ 11s ONSHORE</title>
    <desc lang="en">1.4m and onshore; Lagide will be providing plenty of white water aerobics today.

🌊 Swell: 1.4m @ 11s
💨 Wind: 17.0km/h N (ONSHORE)
💨 Gusts: 29.0km/h
🌊 Wind waves: 0.2m</desc>
    <icon src="https://raw.githubusercontent.com/OiErU/weather-dashboard/main/posters/lagide_poster.jpg" />
  </programme>
  <programme start="20260522180000 +0000" stop="20260523000000 +0000" channel="lagide-meo">
    <title lang="en">🌊 1.4m @ 11s ONSHORE</title>
    <desc lang="en">1.4m and onshore; Lagide will be providing plenty of white water aerobics today.

🌊 Swell: 1.4m @ 11s
💨 Wind: 17.0km/h N (ONSHORE)
💨 Gusts: 29.0km/h
🌊 Wind waves: 0.2m</desc>
    <icon src="https://raw.githubusercontent.com/OiErU/weather-dashboard/main/posters/lagide_poster.jpg" />
  </programme>
  <programme start="20260523000000 +0000" stop="20260523060000 +0000" channel="ericeira-surfline">
    <title lang="en">⭐⭐ 1.5m @ 11s OFFSHORE</title>
    <desc lang="en">With the offshore breeze and a clean 1.5m swell, Ribeira might actually be worth a paddle today.

🌊 Swell: 1.5m @ 11s
💨 Wind: 6.0km/h E (OFFSHORE)
💨 Gusts: 19.0km/h
🌊 Wind waves: 0.3m

📋 Clean conditions with offshore wind</desc>
    <icon src="https://raw.githubusercontent.com/OiErU/weather-dashboard/main/posters/ericeira_poster.jpg" />
  </programme>
  <programme start="20260523000000 +0000" stop="20260523060000 +0000" channel="ericeira-meo">
    <title lang="en">⭐⭐ 1.5m @ 11s OFFSHORE</title>
    <desc lang="en">With the offshore breeze and a clean 1.5m swell, Ribeira might actually be worth a paddle today.

🌊 Swell: 1.5m @ 11s
💨 Wind: 6.0km/h E (OFFSHORE)
💨 Gusts: 19.0km/h
🌊 Wind waves: 0.3m

📋 Clean conditions with offshore wind</desc>
    <icon src="https://raw.githubusercontent.com/OiErU/weather-dashboard/main/posters/ericeira_poster.jpg" />
  </programme>
  <programme start="20260523000000 +0000" stop="20260523060000 +0000" channel="supertubos-surfline">
    <title lang="en">⭐⭐ 1.4m @ 11s OFFSHORE</title>
    <desc lang="en">1.4m and offshore; might manage a cheeky barrel or two, or just get flogged trying.

🌊 Swell: 1.4m @ 11s
💨 Wind: 3.0km/h NNE (OFFSHORE)
💨 Gusts: 16.0km/h
🌊 Wind waves: 0.3m

📋 Clean conditions with offshore wind</desc>
    <icon src="https://raw.githubusercontent.com/OiErU/weather-dashboard/main/posters/supertubos_poster.jpg" />
  </programme>
  <programme start="20260523000000 +0000" stop="20260523060000 +0000" channel="supertubos-meo">
    <title lang="en">⭐⭐ 1.4m @ 11s OFFSHORE</title>
    <desc lang="en">1.4m and offshore; might manage a cheeky barrel or two, or just get flogged trying.

🌊 Swell: 1.4m @ 11s
💨 Wind: 3.0km/h NNE (OFFSHORE)
💨 Gusts: 16.0km/h
🌊 Wind waves: 0.3m

📋 Clean conditions with offshore wind</desc>
    <icon src="https://raw.githubusercontent.com/OiErU/weather-dashboard/main/posters/supertubos_poster.jpg" />
  </programme>
  <programme start="20260523000000 +0000" stop="20260523060000 +0000" channel="molheleste-surfline">
    <title lang="en">🌊 1.4m @ 11s CROSS</title>
    <desc lang="en">1.4m with that crosswind? I've seen worse, but I've definitely seen better.

🌊 Swell: 1.4m @ 11s
💨 Wind: 3.0km/h NNE (CROSS)
💨 Gusts: 16.0km/h
🌊 Wind waves: 0.3m</desc>
    <icon src="https://raw.githubusercontent.com/OiErU/weather-dashboard/main/posters/molheleste_poster.jpg" />
  </programme>
  <programme start="20260523000000 +0000" stop="20260523060000 +0000" channel="molheleste-meo">
    <title lang="en">🌊 1.4m @ 11s CROSS</title>
    <desc lang="en">1.4m with that crosswind? I've seen worse, but I've definitely seen better.

🌊 Swell: 1.4m @ 11s
💨 Wind: 3.0km/h NNE (CROSS)
💨 Gusts: 16.0km/h
🌊 Wind waves: 0.3m</desc>
    <icon src="https://raw.githubusercontent.com/OiErU/weather-dashboard/main/posters/molheleste_poster.jpg" />
  </programme>
  <programme start="20260523000000 +0000" stop="20260523060000 +0000" channel="baia-meo">
    <title lang="en">🌊 1.4m @ 11s CROSS</title>
    <desc lang="en">The 1.4m swell and crosswind might offer a ride or two, or just a cold, sandy beating.

🌊 Swell: 1.4m @ 11s
💨 Wind: 3.0km/h NNE (CROSS)
💨 Gusts: 16.0km/h
🌊 Wind waves: 0.3m</desc>
    <icon src="https://raw.githubusercontent.com/OiErU/weather-dashboard/main/posters/baleal_poster.jpg" />
  </programme>
  <programme start="20260523000000 +0000" stop="20260523060000 +0000" channel="cantinho-surfline">
    <title lang="en">🌊 1.4m @ 11s ONSHORE</title>
    <desc lang="en">With onshore wind and a modest 1.4m swell, Cantinho will offer a few wobbly closeouts, maybe enough for a cold dunking.

🌊 Swell: 1.4m @ 11s
💨 Wind: 3.0km/h NNE (ONSHORE)
💨 Gusts: 16.0km/h
🌊 Wind waves: 0.3m</desc>
    <icon src="https://raw.githubusercontent.com/OiErU/weather-dashboard/main/posters/cantinho_poster.jpg" />
  </programme>
  <programme start="20260523000000 +0000" stop="20260523060000 +0000" channel="cantinho-meo">
    <title lang="en">🌊 1.4m @ 11s ONSHORE</title>
    <desc lang="en">With onshore wind and a modest 1.4m swell, Cantinho will offer a few wobbly closeouts, maybe enough for a cold dunking.

🌊 Swell: 1.4m @ 11s
💨 Wind: 3.0km/h NNE (ONSHORE)
💨 Gusts: 16.0km/h
🌊 Wind waves: 0.3m</desc>
    <icon src="https://raw.githubusercontent.com/OiErU/weather-dashboard/main/posters/cantinho_poster.jpg" />
  </programme>
  <programme start="20260523000000 +0000" stop="20260523060000 +0000" channel="baleal-surfline">
    <title lang="en">🌊 1.4m @ 11s ONSHORE</title>
    <desc lang="en">At 1.4m and with that onshore breeze, Baleal Norte will likely provide some bumpy, short rides today.

🌊 Swell: 1.4m @ 11s
💨 Wind: 3.0km/h NNE (ONSHORE)
💨 Gusts: 16.0km/h
🌊 Wind waves: 0.3m</desc>
    <icon src="https://raw.githubusercontent.com/OiErU/weather-dashboard/main/posters/baleal_poster.jpg" />
  </programme>
  <programme start="20260523000000 +0000" stop="20260523060000 +0000" channel="lagide-surfline">
    <title lang="en">🌊 1.4m @ 11s ONSHORE</title>
    <desc lang="en">That 1.4m swell and onshore breeze suggests a guaranteed workout, at least.

🌊 Swell: 1.4m @ 11s
💨 Wind: 3.0km/h NNE (ONSHORE)
💨 Gusts: 16.0km/h
🌊 Wind waves: 0.3m</desc>
    <icon src="https://raw.githubusercontent.com/OiErU/weather-dashboard/main/posters/lagide_poster.jpg" />
  </programme>
  <programme start="20260523000000 +0000" stop="20260523060000 +0000" channel="lagide-meo">
    <title lang="en">🌊 1.4m @ 11s ONSHORE</title>
    <desc lang="en">That 1.4m swell and onshore breeze suggests a guaranteed workout, at least.

🌊 Swell: 1.4m @ 11s
💨 Wind: 3.0km/h NNE (ONSHORE)
💨 Gusts: 16.0km/h
🌊 Wind waves: 0.3m</desc>
    <icon src="https://raw.githubusercontent.com/OiErU/weather-dashboard/main/posters/lagide_poster.jpg" />
  </programme>
  <programme start="20260523060000 +0000" stop="20260523120000 +0000" channel="ericeira-surfline">
    <title lang="en">🌊 1.5m @ 11s CROSS</title>
    <desc lang="en">At 1.5m and with that wind, Ribeira will be...surfable, maybe, if you're feeling generous.

🌊 Swell: 1.5m @ 11s
💨 Wind: 8.0km/h N (CROSS)
💨 Gusts: 18.0km/h
🌊 Wind waves: 0.3m</desc>
    <icon src="https://raw.githubusercontent.com/OiErU/weather-dashboard/main/posters/ericeira_poster.jpg" />
  </programme>
  <programme start="20260523060000 +0000" stop="20260523120000 +0000" channel="ericeira-meo">
    <title lang="en">🌊 1.5m @ 11s CROSS</title>
    <desc lang="en">At 1.5m and with that wind, Ribeira will be...surfable, maybe, if you're feeling generous.

🌊 Swell: 1.5m @ 11s
💨 Wind: 8.0km/h N (CROSS)
💨 Gusts: 18.0km/h
🌊 Wind waves: 0.3m</desc>
    <icon src="https://raw.githubusercontent.com/OiErU/weather-dashboard/main/posters/ericeira_poster.jpg" />
  </programme>
  <programme start="20260523060000 +0000" stop="20260523120000 +0000" channel="supertubos-surfline">
    <title lang="en">🌊 1.4m @ 11s CROSS</title>
    <desc lang="en">At 1.4m, and with that wind, today will mostly involve getting sandblasted between closeouts.

🌊 Swell: 1.4m @ 11s
💨 Wind: 13.0km/h N (CROSS)
💨 Gusts: 24.0km/h
🌊 Wind waves: 0.3m</desc>
    <icon src="https://raw.githubusercontent.com/OiErU/weather-dashboard/main/posters/supertubos_poster.jpg" />
  </programme>
  <programme start="20260523060000 +0000" stop="20260523120000 +0000" channel="supertubos-meo">
    <title lang="en">🌊 1.4m @ 11s CROSS</title>
    <desc lang="en">At 1.4m, and with that wind, today will mostly involve getting sandblasted between closeouts.

🌊 Swell: 1.4m @ 11s
💨 Wind: 13.0km/h N (CROSS)
💨 Gusts: 24.0km/h
🌊 Wind waves: 0.3m</desc>
    <icon src="https://raw.githubusercontent.com/OiErU/weather-dashboard/main/posters/supertubos_poster.jpg" />
  </programme>
  <programme start="20260523060000 +0000" stop="20260523120000 +0000" channel="molheleste-surfline">
    <title lang="en">🌊 1.4m @ 11s CROSS</title>
    <desc lang="en">1.4 meters with that wind; might be some bumpy rides for the truly desperate.

🌊 Swell: 1.4m @ 11s
💨 Wind: 13.0km/h N (CROSS)
💨 Gusts: 24.0km/h
🌊 Wind waves: 0.3m</desc>
    <icon src="https://raw.githubusercontent.com/OiErU/weather-dashboard/main/posters/molheleste_poster.jpg" />
  </programme>
  <programme start="20260523060000 +0000" stop="20260523120000 +0000" channel="molheleste-meo">
    <title lang="en">🌊 1.4m @ 11s CROSS</title>
    <desc lang="en">1.4 meters with that wind; might be some bumpy rides for the truly desperate.

🌊 Swell: 1.4m @ 11s
💨 Wind: 13.0km/h N (CROSS)
💨 Gusts: 24.0km/h
🌊 Wind waves: 0.3m</desc>
    <icon src="https://raw.githubusercontent.com/OiErU/weather-dashboard/main/posters/molheleste_poster.jpg" />
  </programme>
  <programme start="20260523060000 +0000" stop="20260523120000 +0000" channel="baia-meo">
    <title lang="en">🌊 1.4m @ 11s ONSHORE</title>
    <desc lang="en">With a 1.4m swell and onshore breeze, today's session will be a character-building experience, at best.

🌊 Swell: 1.4m @ 11s
💨 Wind: 13.0km/h N (ONSHORE)
💨 Gusts: 24.0km/h
🌊 Wind waves: 0.3m</desc>
    <icon src="https://raw.githubusercontent.com/OiErU/weather-dashboard/main/posters/baleal_poster.jpg" />
  </programme>
  <programme start="20260523060000 +0000" stop="20260523120000 +0000" channel="cantinho-surfline">
    <title lang="en">🌊 1.4m @ 11s ONSHORE</title>
    <desc lang="en">With 1.4m and onshore wind, today's session will either be an exercise in frustration or an early trip to the beach bar.

🌊 Swell: 1.4m @ 11s
💨 Wind: 13.0km/h N (ONSHORE)
💨 Gusts: 24.0km/h
🌊 Wind waves: 0.3m</desc>
    <icon src="https://raw.githubusercontent.com/OiErU/weather-dashboard/main/posters/cantinho_poster.jpg" />
  </programme>
  <programme start="20260523060000 +0000" stop="20260523120000 +0000" channel="cantinho-meo">
    <title lang="en">🌊 1.4m @ 11s ONSHORE</title>
    <desc lang="en">With 1.4m and onshore wind, today's session will either be an exercise in frustration or an early trip to the beach bar.

🌊 Swell: 1.4m @ 11s
💨 Wind: 13.0km/h N (ONSHORE)
💨 Gusts: 24.0km/h
🌊 Wind waves: 0.3m</desc>
    <icon src="https://raw.githubusercontent.com/OiErU/weather-dashboard/main/posters/cantinho_poster.jpg" />
  </programme>
  <programme start="20260523060000 +0000" stop="20260523120000 +0000" channel="baleal-surfline">
    <title lang="en">🌊 1.4m @ 11s ONSHORE</title>
    <desc lang="en">With 1.4m and onshore breeze, it might be rideable if you like battling chop and getting blown back to Peniche.

🌊 Swell: 1.4m @ 11s
💨 Wind: 13.0km/h N (ONSHORE)
💨 Gusts: 24.0km/h
🌊 Wind waves: 0.3m</desc>
    <icon src="https://raw.githubusercontent.com/OiErU/weather-dashboard/main/posters/baleal_poster.jpg" />
  </programme>
  <programme start="20260523060000 +0000" stop="20260523120000 +0000" channel="lagide-surfline">
    <title lang="en">🌊 1.4m @ 11s ONSHORE</title>
    <desc lang="en">A choppy 1.4m of onshore grief awaits those keen on a pounding.

🌊 Swell: 1.4m @ 11s
💨 Wind: 13.0km/h N (ONSHORE)
💨 Gusts: 24.0km/h
🌊 Wind waves: 0.3m</desc>
    <icon src="https://raw.githubusercontent.com/OiErU/weather-dashboard/main/posters/lagide_poster.jpg" />
  </programme>
  <programme start="20260523060000 +0000" stop="20260523120000 +0000" channel="lagide-meo">
    <title lang="en">🌊 1.4m @ 11s ONSHORE</title>
    <desc lang="en">A choppy 1.4m of onshore grief awaits those keen on a pounding.

🌊 Swell: 1.4m @ 11s
💨 Wind: 13.0km/h N (ONSHORE)
💨 Gusts: 24.0km/h
🌊 Wind waves: 0.3m</desc>
    <icon src="https://raw.githubusercontent.com/OiErU/weather-dashboard/main/posters/lagide_poster.jpg" />
  </programme>
  <programme start="20260523120000 +0000" stop="20260523180000 +0000" channel="ericeira-surfline">
    <title lang="en">🌊 1.3m @ 11s CROSS</title>
    <desc lang="en">Those 1.3m waves will offer some rides, assuming the wind doesn't blow you to Spain.

🌊 Swell: 1.3m @ 11s
💨 Wind: 14.0km/h N (CROSS)
💨 Gusts: 30.0km/h
🌊 Wind waves: 0.5m</desc>
    <icon src="https://raw.githubusercontent.com/OiErU/weather-dashboard/main/posters/ericeira_poster.jpg" />
  </programme>
  <programme start="20260523120000 +0000" stop="20260523180000 +0000" channel="ericeira-meo">
    <title lang="en">🌊 1.3m @ 11s CROSS</title>
    <desc lang="en">Those 1.3m waves will offer some rides, assuming the wind doesn't blow you to Spain.

🌊 Swell: 1.3m @ 11s
💨 Wind: 14.0km/h N (CROSS)
💨 Gusts: 30.0km/h
🌊 Wind waves: 0.5m</desc>
    <icon src="https://raw.githubusercontent.com/OiErU/weather-dashboard/main/posters/ericeira_poster.jpg" />
  </programme>
  <programme start="20260523120000 +0000" stop="20260523180000 +0000" channel="supertubos-surfline">
    <title lang="en">🌊 1.3m @ 11s CROSS</title>
    <desc lang="en">A 1.3m swell and cross-wind mean it'll be a workout paddling to the peak for whatever reforms.

🌊 Swell: 1.3m @ 11s
💨 Wind: 16.0km/h N (CROSS)
💨 Gusts: 28.0km/h
🌊 Wind waves: 0.4m</desc>
    <icon src="https://raw.githubusercontent.com/OiErU/weather-dashboard/main/posters/supertubos_poster.jpg" />
  </programme>
  <programme start="20260523120000 +0000" stop="20260523180000 +0000" channel="supertubos-meo">
    <title lang="en">🌊 1.3m @ 11s CROSS</title>
    <desc lang="en">A 1.3m swell and cross-wind mean it'll be a workout paddling to the peak for whatever reforms.

🌊 Swell: 1.3m @ 11s
💨 Wind: 16.0km/h N (CROSS)
💨 Gusts: 28.0km/h
🌊 Wind waves: 0.4m</desc>
    <icon src="https://raw.githubusercontent.com/OiErU/weather-dashboard/main/posters/supertubos_poster.jpg" />
  </programme>
  <programme start="20260523120000 +0000" stop="20260523180000 +0000" channel="molheleste-surfline">
    <title lang="en">🌊 1.3m @ 11s CROSS</title>
    <desc lang="en">The 1.3m swell and crosswind suggest a session of fighting chop for small victories.

🌊 Swell: 1.3m @ 11s
💨 Wind: 16.0km/h N (CROSS)
💨 Gusts: 28.0km/h
🌊 Wind waves: 0.4m</desc>
    <icon src="https://raw.githubusercontent.com/OiErU/weather-dashboard/main/posters/molheleste_poster.jpg" />
  </programme>
  <programme start="20260523120000 +0000" stop="20260523180000 +0000" channel="molheleste-meo">
    <title lang="en">🌊 1.3m @ 11s CROSS</title>
    <desc lang="en">The 1.3m swell and crosswind suggest a session of fighting chop for small victories.

🌊 Swell: 1.3m @ 11s
💨 Wind: 16.0km/h N (CROSS)
💨 Gusts: 28.0km/h
🌊 Wind waves: 0.4m</desc>
    <icon src="https://raw.githubusercontent.com/OiErU/weather-dashboard/main/posters/molheleste_poster.jpg" />
  </programme>
  <programme start="20260523120000 +0000" stop="20260523180000 +0000" channel="baia-meo">
    <title lang="en">🌊 1.3m @ 11s ONSHORE</title>
    <desc lang="en">The 1.3m swell with that onshore wind? Probably better for a walk on the beach than a bodyboard.

🌊 Swell: 1.3m @ 11s
💨 Wind: 16.0km/h N (ONSHORE)
💨 Gusts: 28.0km/h
🌊 Wind waves: 0.4m</desc>
    <icon src="https://raw.githubusercontent.com/OiErU/weather-dashboard/main/posters/baleal_poster.jpg" />
  </programme>
  <programme start="20260523120000 +0000" stop="20260523180000 +0000" channel="cantinho-surfline">
    <title lang="en">🌊 1.3m @ 11s ONSHORE</title>
    <desc lang="en">Those 1.3m waves will be bumpy and short-lived, perfect for refining one's sand-avoidance techniques.

🌊 Swell: 1.3m @ 11s
💨 Wind: 16.0km/h N (ONSHORE)
💨 Gusts: 28.0km/h
🌊 Wind waves: 0.4m</desc>
    <icon src="https://raw.githubusercontent.com/OiErU/weather-dashboard/main/posters/cantinho_poster.jpg" />
  </programme>
  <programme start="20260523120000 +0000" stop="20260523180000 +0000" channel="cantinho-meo">
    <title lang="en">🌊 1.3m @ 11s ONSHORE</title>
    <desc lang="en">Those 1.3m waves will be bumpy and short-lived, perfect for refining one's sand-avoidance techniques.

🌊 Swell: 1.3m @ 11s
💨 Wind: 16.0km/h N (ONSHORE)
💨 Gusts: 28.0km/h
🌊 Wind waves: 0.4m</desc>
    <icon src="https://raw.githubusercontent.com/OiErU/weather-dashboard/main/posters/cantinho_poster.jpg" />
  </programme>
  <programme start="20260523120000 +0000" stop="20260523180000 +0000" channel="baleal-surfline">
    <title lang="en">🌊 1.3m @ 11s ONSHORE</title>
    <desc lang="en">With onshore breeze and a meter-plus swell, expect some wobbly closeouts and a good swim.

🌊 Swell: 1.3m @ 11s
💨 Wind: 16.0km/h N (ONSHORE)
💨 Gusts: 28.0km/h
🌊 Wind waves: 0.4m</desc>
    <icon src="https://raw.githubusercontent.com/OiErU/weather-dashboard/main/posters/baleal_poster.jpg" />
  </programme>
  <programme start="20260523120000 +0000" stop="20260523180000 +0000" channel="lagide-surfline">
    <title lang="en">🌊 1.3m @ 11s ONSHORE</title>
    <desc lang="en">That 1.3m swell with onshore wind suggests a choppy morning workout, if you're feeling masochistic.

🌊 Swell: 1.3m @ 11s
💨 Wind: 16.0km/h N (ONSHORE)
💨 Gusts: 28.0km/h
🌊 Wind waves: 0.4m</desc>
    <icon src="https://raw.githubusercontent.com/OiErU/weather-dashboard/main/posters/lagide_poster.jpg" />
  </programme>
  <programme start="20260523120000 +0000" stop="20260523180000 +0000" channel="lagide-meo">
    <title lang="en">🌊 1.3m @ 11s ONSHORE</title>
    <desc lang="en">That 1.3m swell with onshore wind suggests a choppy morning workout, if you're feeling masochistic.

🌊 Swell: 1.3m @ 11s
💨 Wind: 16.0km/h N (ONSHORE)
💨 Gusts: 28.0km/h
🌊 Wind waves: 0.4m</desc>
    <icon src="https://raw.githubusercontent.com/OiErU/weather-dashboard/main/posters/lagide_poster.jpg" />
  </programme>
  <programme start="20260523180000 +0000" stop="20260524000000 +0000" channel="ericeira-surfline">
    <title lang="en">🌊 1.2m @ 10s CROSS</title>
    <desc lang="en">A 1.2m swell and cross-shore breeze suggests a fairly average day for getting mildly worked.

🌊 Swell: 1.2m @ 10s
💨 Wind: 13.0km/h NW (CROSS)
💨 Gusts: 26.0km/h
🌊 Wind waves: 0.6m</desc>
    <icon src="https://raw.githubusercontent.com/OiErU/weather-dashboard/main/posters/ericeira_poster.jpg" />
  </programme>
  <programme start="20260523180000 +0000" stop="20260524000000 +0000" channel="ericeira-meo">
    <title lang="en">🌊 1.2m @ 10s CROSS</title>
    <desc lang="en">A 1.2m swell and cross-shore breeze suggests a fairly average day for getting mildly worked.

🌊 Swell: 1.2m @ 10s
💨 Wind: 13.0km/h NW (CROSS)
💨 Gusts: 26.0km/h
🌊 Wind waves: 0.6m</desc>
    <icon src="https://raw.githubusercontent.com/OiErU/weather-dashboard/main/posters/ericeira_poster.jpg" />
  </programme>
  <programme start="20260523180000 +0000" stop="20260524000000 +0000" channel="supertubos-surfline">
    <title lang="en">🌊 1.2m @ 10s CROSS</title>
    <desc lang="en">The 1.2m swell and cross-wind suggest a session of battling wonky ramps, punctuated by long swims.

🌊 Swell: 1.2m @ 10s
💨 Wind: 14.0km/h NW (CROSS)
💨 Gusts: 24.0km/h
🌊 Wind waves: 0.5m</desc>
    <icon src="https://raw.githubusercontent.com/OiErU/weather-dashboard/main/posters/supertubos_poster.jpg" />
  </programme>
  <programme start="20260523180000 +0000" stop="20260524000000 +0000" channel="supertubos-meo">
    <title lang="en">🌊 1.2m @ 10s CROSS</title>
    <desc lang="en">The 1.2m swell and cross-wind suggest a session of battling wonky ramps, punctuated by long swims.

🌊 Swell: 1.2m @ 10s
💨 Wind: 14.0km/h NW (CROSS)
💨 Gusts: 24.0km/h
🌊 Wind waves: 0.5m</desc>
    <icon src="https://raw.githubusercontent.com/OiErU/weather-dashboard/main/posters/supertubos_poster.jpg" />
  </programme>
  <programme start="20260523180000 +0000" stop="20260524000000 +0000" channel="molheleste-surfline">
    <title lang="en">🌊 1.2m @ 10s CROSS</title>
    <desc lang="en">The 1.2m swell and crosswind might offer a few rides, or just a face full of Atlantic grit.

🌊 Swell: 1.2m @ 10s
💨 Wind: 14.0km/h NW (CROSS)
💨 Gusts: 24.0km/h
🌊 Wind waves: 0.5m</desc>
    <icon src="https://raw.githubusercontent.com/OiErU/weather-dashboard/main/posters/molheleste_poster.jpg" />
  </programme>
  <programme start="20260523180000 +0000" stop="20260524000000 +0000" channel="molheleste-meo">
    <title lang="en">🌊 1.2m @ 10s CROSS</title>
    <desc lang="en">The 1.2m swell and crosswind might offer a few rides, or just a face full of Atlantic grit.

🌊 Swell: 1.2m @ 10s
💨 Wind: 14.0km/h NW (CROSS)
💨 Gusts: 24.0km/h
🌊 Wind waves: 0.5m</desc>
    <icon src="https://raw.githubusercontent.com/OiErU/weather-dashboard/main/posters/molheleste_poster.jpg" />
  </programme>
  <programme start="20260523180000 +0000" stop="20260524000000 +0000" channel="baia-meo">
    <title lang="en">🌊 1.2m @ 10s ONSHORE</title>
    <desc lang="en">That onshore breeze will likely turn those 1.2m waves into a bumpy washing machine, best suited for practicing rescues.

🌊 Swell: 1.2m @ 10s
💨 Wind: 14.0km/h NW (ONSHORE)
💨 Gusts: 24.0km/h
🌊 Wind waves: 0.5m</desc>
    <icon src="https://raw.githubusercontent.com/OiErU/weather-dashboard/main/posters/baleal_poster.jpg" />
  </programme>
  <programme start="20260523180000 +0000" stop="20260524000000 +0000" channel="cantinho-surfline">
    <title lang="en">🌊 1.2m @ 10s ONSHORE</title>
    <desc lang="en">Those 1.2m waves might offer a ride or two before the onshore wind turns them into something resembling choppy soup.

🌊 Swell: 1.2m @ 10s
💨 Wind: 14.0km/h NW (ONSHORE)
💨 Gusts: 24.0km/h
🌊 Wind waves: 0.5m</desc>
    <icon src="https://raw.githubusercontent.com/OiErU/weather-dashboard/main/posters/cantinho_poster.jpg" />
  </programme>
  <programme start="20260523180000 +0000" stop="20260524000000 +0000" channel="cantinho-meo">
    <title lang="en">🌊 1.2m @ 10s ONSHORE</title>
    <desc lang="en">Those 1.2m waves might offer a ride or two before the onshore wind turns them into something resembling choppy soup.

🌊 Swell: 1.2m @ 10s
💨 Wind: 14.0km/h NW (ONSHORE)
💨 Gusts: 24.0km/h
🌊 Wind waves: 0.5m</desc>
    <icon src="https://raw.githubusercontent.com/OiErU/weather-dashboard/main/posters/cantinho_poster.jpg" />
  </programme>
  <programme start="20260523180000 +0000" stop="20260524000000 +0000" channel="baleal-surfline">
    <title lang="en">🌊 1.2m @ 10s ONSHORE</title>
    <desc lang="en">That 1.2m of chop will probably leave you sand-rashed and vaguely questioning your life choices.

🌊 Swell: 1.2m @ 10s
💨 Wind: 14.0km/h NW (ONSHORE)
💨 Gusts: 24.0km/h
🌊 Wind waves: 0.5m</desc>
    <icon src="https://raw.githubusercontent.com/OiErU/weather-dashboard/main/posters/baleal_poster.jpg" />
  </programme>
  <programme start="20260523180000 +0000" stop="20260524000000 +0000" channel="lagide-surfline">
    <title lang="en">🌊 1.2m @ 10s ONSHORE</title>
    <desc lang="en">With 1.2m and onshore wind, today's Lagide will likely deliver a mixed bag of chop and closeouts.

🌊 Swell: 1.2m @ 10s
💨 Wind: 14.0km/h NW (ONSHORE)
💨 Gusts: 24.0km/h
🌊 Wind waves: 0.5m</desc>
    <icon src="https://raw.githubusercontent.com/OiErU/weather-dashboard/main/posters/lagide_poster.jpg" />
  </programme>
  <programme start="20260523180000 +0000" stop="20260524000000 +0000" channel="lagide-meo">
    <title lang="en">🌊 1.2m @ 10s ONSHORE</title>
    <desc lang="en">With 1.2m and onshore wind, today's Lagide will likely deliver a mixed bag of chop and closeouts.

🌊 Swell: 1.2m @ 10s
💨 Wind: 14.0km/h NW (ONSHORE)
💨 Gusts: 24.0km/h
🌊 Wind waves: 0.5m</desc>
    <icon src="https://raw.githubusercontent.com/OiErU/weather-dashboard/main/posters/lagide_poster.jpg" />
  </programme>
</tv>